Workbook

Sheet Assumptions
A1: SKU MASTER DATA
A2: Product costs, pricing, and inventory parameters
A4: SKU ID | B4: Product Name | C4: Unit Cost | D4: DTC Price | E4: Wholesale Price | F4: Lead Time (Mo) | G4: Safety Stock | H4: Current Inventory | I4: MOQ
A5: SKU001 | B5: Monarch Steel - Black | C5: 120 | D5: 343.99 | E5: 275 | F5: 3 | G5: 100 | H5: 250 | I5: 50
A6: SKU002 | B6: Monarch Steel - White | C6: 120 | D6: 343.99 | E6: 275 | F6: 3 | G6: 100 | H6: 180 | I6: 50
A7: SKU003 | B7: Monarch Steel - Pink | C7: 120 | D7: 343.99 | E7: 275 | F7: 3 | G7: 80 | H7: 150 | I7: 50
A8: SKU004 | B8: Monarch Steel - Blue | C8: 120 | D8: 343.99 | E8: 275 | F8: 3 | G8: 80 | H8: 120 | I8: 50
A9: SKU005 | B9: Monarch Midnight - Black | C9: 125 | D9: 343.99 | E9: 280 | F9: 3 | G9: 80 | H9: 110 | I9: 50
A10: SKU006 | B10: Monarch Midnight - White | C10: 125 | D10: 343.99 | E10: 280 | F10: 3 | G10: 70 | H10: 90 | I10: 50
A11: SKU007 | B11: Ball Markr Tool | C11: 3.5 | D11: 8.99 | E11: 6.5 | F11: 2 | G11: 500 | H11: 800 | I11: 200
A12: SKU008 | B12: Gate Trainr | C12: 4 | D12: 8.99 | E12: 6.5 | F12: 2 | G12: 400 | H12: 600 | I12: 200
A13: SKU009 | B13: Blade Headcover | C13: 8 | D13: 19.99 | E13: 14 | F13: 2 | G13: 200 | H13: 350 | I13: 100
A14: SKU010 | B14: Accessories Bundle | C14: 25 | D14: 49.99 | E14: 35 | F14: 2 | G14: 150 | H14: 300 | I14: 75
A16: 📋 DEFINITIONS
A17: • Unit Cost = Manufacturing cost per item (COGS)
A18: • Lead Time = Months from order placement to warehouse arrival
A19: • Safety Stock = Minimum inventory before triggering reorder alert
A20: • MOQ = Minimum order quantity required by manufacturer

Sheet Demand Forecast
A1: DEMAND FORECAST
A2: 12-month sales projections by channel
A4: DTC / ONLINE SALES
A5: SKU | B5: Channel | C5: January | D5: February | E5: March | F5: April | G5: May | H5: June | I5: July | J5: August | K5: September | L5: October | M5: November | N5: December
A6: SKU001 | B6: DTC | C6: 15 | D6: 18 | E6: 20 | F6: 22 | G6: 25 | H6: 28 | I6: 30 | J6: 32 | K6: 35 | L6: 38 | M6: 40 | N6: 45
A7: SKU002 | B7: DTC | C7: 12 | D7: 14 | E7: 16 | F7: 18 | G7: 20 | H7: 22 | I7: 24 | J7: 26 | K7: 28 | L7: 30 | M7: 32 | N7: 35
A8: SKU003 | B8: DTC | C8: 10 | D8: 12 | E8: 14 | F8: 15 | G8: 17 | H8: 19 | I8: 21 | J8: 23 | K8: 25 | L8: 27 | M8: 29 | N8: 32
A9: SKU004 | B9: DTC | C9: 8 | D9: 10 | E9: 11 | F9: 13 | G9: 15 | H9: 17 | I9: 19 | J9: 21 | K9: 23 | L9: 25 | M9: 27 | N9: 30
A10: SKU005 | B10: DTC | C10: 7 | D10: 9 | E10: 10 | F10: 12 | G10: 14 | H10: 16 | I10: 18 | J10: 20 | K10: 22 | L10: 24 | M10: 26 | N10: 28
A11: SKU006 | B11: DTC | C11: 6 | D11: 8 | E11: 9 | F11: 11 | G11: 13 | H11: 15 | I11: 17 | J11: 19 | K11: 21 | L11: 23 | M11: 25 | N11: 27
A12: SKU007 | B12: DTC | C12: 50 | D12: 55 | E12: 60 | F12: 65 | G12: 70 | H12: 75 | I12: 80 | J12: 85 | K12: 90 | L12: 95 | M12: 100 | N12: 110
A13: SKU008 | B13: DTC | C13: 40 | D13: 45 | E13: 50 | F13: 55 | G13: 60 | H13: 65 | I13: 70 | J13: 75 | K13: 80 | L13: 85 | M13: 90 | N13: 95
A14: SKU009 | B14: DTC | C14: 30 | D14: 35 | E14: 40 | F14: 45 | G14: 50 | H14: 55 | I14: 60 | J14: 65 | K14: 70 | L14: 75 | M14: 80 | N14: 85
A15: SKU010 | B15: DTC | C15: 25 | D15: 28 | E15: 30 | F15: 33 | G15: 36 | H15: 40 | I15: 44 | J15: 48 | K15: 52 | L15: 56 | M15: 60 | N15: 65
A16: RETAIL / WHOLESALE ORDERS
A17: SKU | B17: Channel | C17: January | D17: February | E17: March | F17: April | G17: May | H17: June | I17: July | J17: August | K17: September | L17: October | M17: November | N17: December
A18: SKU001 | B18: Company X | C18: 0 | D18: 0 | E18: 150 | F18: 0 | G18: 0 | H18: 0 | I18: 200 | J18: 0 | K18: 0 | L18: 0 | M18: 250 | N18: 0
A19: SKU001 | B19: Company Y | C19: 0 | D19: 100 | E19: 0 | F19: 0 | G19: 0 | H19: 150 | I19: 0 | J19: 0 | K19: 0 | L19: 200 | M19: 0 | N19: 0
A20: SKU002 | B20: Company X | C20: 0 | D20: 0 | E20: 100 | F20: 0 | G20: 0 | H20: 0 | I20: 150 | J20: 0 | K20: 0 | L20: 0 | M20: 200 | N20: 0
A21: SKU002 | B21: Company Y | C21: 0 | D21: 75 | E21: 0 | F21: 0 | G21: 0 | H21: 100 | I21: 0 | J21: 0 | K21: 0 | L21: 125 | M21: 0 | N21: 0
A22: SKU003 | B22: Company X | C22: 0 | D22: 0 | E22: 80 | F22: 0 | G22: 0 | H22: 0 | I22: 120 | J22: 0 | K22: 0 | L22: 0 | M22: 150 | N22: 0
A23: SKU003 | B23: Company Y | C23: 0 | D23: 60 | E23: 0 | F23: 0 | G23: 0 | H23: 80 | I23: 0 | J23: 0 | K23: 0 | L23: 100 | M23: 0 | N23: 0
A24: SKU004 | B24: Company X | C24: 0 | D24: 0 | E24: 50 | F24: 0 | G24: 0 | H24: 0 | I24: 80 | J24: 0 | K24: 0 | L24: 0 | M24: 100 | N24: 0
A25: SKU004 | B25: Company Y | C25: 0 | D25: 40 | E25: 0 | F25: 0 | G25: 0 | H25: 60 | I25: 0 | J25: 0 | K25: 0 | L25: 75 | M25: 0 | N25: 0
A26: SKU005 | B26: Company X | C26: 0 | D26: 0 | E26: 40 | F26: 0 | G26: 0 | H26: 0 | I26: 70 | J26: 0 | K26: 0 | L26: 0 | M26: 90 | N26: 0
A27: SKU005 | B27: Company Y | C27: 0 | D27: 35 | E27: 0 | F27: 0 | G27: 0 | H27: 55 | I27: 0 | J27: 0 | K27: 0 | L27: 70 | M27: 0 | N27: 0
A28: SKU006 | B28: Company X | C28: 0 | D28: 0 | E28: 0 | F28: 0 | G28: 0 | H28: 0 | I28: 0 | J28: 0 | K28: 0 | L28: 0 | M28: 0 | N28: 0
A29: SKU006 | B29: Company Y | C29: 0 | D29: 0 | E29: 0 | F29: 0 | G29: 0 | H29: 0 | I29: 0 | J29: 0 | K29: 0 | L29: 0 | M29: 0 | N29: 0
... A37: SKU010 | B37: Company Y | C37: 0 | D37: 0 | E37: 0 | F37: 0 | G37: 0 | H37: 0 | I37: 0 | J37: 0 | K37: 0 | L37: 0 | M37: 0 | N37: 0
A38: TOTAL DEMAND (ALL CHANNELS)
A39: SKU | C39: January | D39: February | E39: March | F39: April | G39: May | H39: June | I39: July | J39: August | K39: September | L39: October | M39: November | N39: December
A40: SKU001 | B40: TOTAL | C40: =C6+C18+C19 -> 15 | D40: =D6+D18+D19 -> 118 | E40: =E6+E18+E19 -> 170 | F40: =F6+F18+F19 -> 22 | G40: =G6+G18+G19 -> 25 | H40: =H6+H18+H19 -> 178 | I40: =I6+I18+I19 -> 230 | J40: =J6+J18+J19 -> 32 | ... N40: =N6+N18+N19 -> 45
A41: SKU002 | B41: TOTAL | C41: =C7+C20+C21 -> 12 | D41: =D7+D20+D21 -> 89 | E41: =E7+E20+E21 -> 116 | F41: =F7+F20+F21 -> 18 | G41: =G7+G20+G21 -> 20 | H41: =H7+H20+H21 -> 122 | I41: =I7+I20+I21 -> 174 | J41: =J7+J20+J21 -> 26 | ... N41: =N7+N20+N21 -> 35
A42: SKU003 | B42: TOTAL | C42: =C8+C22+C23 -> 10 | D42: =D8+D22+D23 -> 72 | E42: =E8+E22+E23 -> 94 | F42: =F8+F22+F23 -> 15 | G42: =G8+G22+G23 -> 17 | H42: =H8+H22+H23 -> 99 | I42: =I8+I22+I23 -> 141 | J42: =J8+J22+J23 -> 23 | ... N42: =N8+N22+N23 -> 32
A43: SKU004 | B43: TOTAL | C43: =C9+C24+C25 -> 8 | D43: =D9+D24+D25 -> 50 | E43: =E9+E24+E25 -> 61 | F43: =F9+F24+F25 -> 13 | G43: =G9+G24+G25 -> 15 | H43: =H9+H24+H25 -> 77 | I43: =I9+I24+I25 -> 99 | J43: =J9+J24+J25 -> 21 | ... N43: =N9+N24+N25 -> 30
A44: SKU005 | B44: TOTAL | C44: =C10+C26+C27 -> 7 | D44: =D10+D26+D27 -> 44 | E44: =E10+E26+E27 -> 50 | F44: =F10+F26+F27 -> 12 | G44: =G10+G26+G27 -> 14 | H44: =H10+H26+H27 -> 71 | I44: =I10+I26+I27 -> 88 | J44: =J10+J26+J27 -> 20 | ... N44: =N10+N26+N27 -> 28
A45: SKU006 | B45: TOTAL | C45: =C11+C28+C29 -> 6 | D45: =D11+D28+D29 -> 8 | E45: =E11+E28+E29 -> 9 | F45: =F11+F28+F29 -> 11 | G45: =G11+G28+G29 -> 13 | H45: =H11+H28+H29 -> 15 | I45: =I11+I28+I29 -> 17 | J45: =J11+J28+J29 -> 19 | ... N45: =N11+N28+N29 -> 27
A46: SKU007 | B46: TOTAL | C46: =C12+C30+C31 -> 50 | D46: =D12+D30+D31 -> 55 | E46: =E12+E30+E31 -> 60 | F46: =F12+F30+F31 -> 65 | G46: =G12+G30+G31 -> 70 | H46: =H12+H30+H31 -> 75 | I46: =I12+I30+I31 -> 80 | J46: =J12+J30+J31 -> 85 | ... N46: =N12+N30+N31 -> 110
A47: SKU008 | B47: TOTAL | C47: =C13+C32+C33 -> 40 | D47: =D13+D32+D33 -> 45 | E47: =E13+E32+E33 -> 50 | F47: =F13+F32+F33 -> 55 | G47: =G13+G32+G33 -> 60 | H47: =H13+H32+H33 -> 65 | I47: =I13+I32+I33 -> 70 | J47: =J13+J32+J33 -> 75 | ... N47: =N13+N32+N33 -> 95
A48: SKU009 | B48: TOTAL | C48: =C14+C34+C35 -> 30 | D48: =D14+D34+D35 -> 35 | E48: =E14+E34+E35 -> 40 | F48: =F14+F34+F35 -> 45 | G48: =G14+G34+G35 -> 50 | H48: =H14+H34+H35 -> 55 | I48: =I14+I34+I35 -> 60 | J48: =J14+J34+J35 -> 65 | ... N48: =N14+N34+N35 -> 85
A49: SKU010 | B49: TOTAL | C49: =C15+C36+C37 -> 25 | D49: =D15+D36+D37 -> 28 | E49: =E15+E36+E37 -> 30 | F49: =F15+F36+F37 -> 33 | G49: =G15+G36+G37 -> 36 | H49: =H15+H36+H37 -> 40 | I49: =I15+I36+I37 -> 44 | J49: =J15+J36+J37 -> 48 | ... N49: =N15+N36+N37 -> 65

Sheet Inventory Model
A1: INVENTORY MODEL
A2: Real-time inventory tracking with lead-time-aware reorder alerts
A4: SKU | B4: Metric | C4: January | D4: February | E4: March | F4: April | G4: May | H4: June | I4: July | J4: August | K4: September | L4: October | M4: November | N4: December | O4: Status
A5: SKU001 | B5: Beginning Inventory | C5: =Assumptions!H5 -> 250 | D5: =C9 -> 235 | E5: =D9 -> 117 | F5: =E9 -> 0 | G5: =F9 -> 0 | H5: =G9 -> 0 | I5: =H9 -> 0 | J5: =I9 -> 0 | K5: =J9 -> 0 | ... N5: =M9 -> 0
B6: Gross Sales | C6: ='Demand Forecast'!C40 -> 15 | D6: ='Demand Forecast'!D40 -> 118 | E6: ='Demand Forecast'!E40 -> 170 | F6: ='Demand Forecast'!F40 -> 22 | G6: ='Demand Forecast'!G40 -> 25 | H6: ='Demand Forecast'!H40 -> 178 | I6: ='Demand Forecast'!I40 -> 230 | J6: ='Demand Forecast'!J40 -> 32 | ... N6: ='Demand Forecast'!N40 -> 45
B7: Net Position | C7: =C5-C6 -> 235 | D7: =D5-D6 -> 117 | E7: =E5-E6 -> -53 | F7: =F5-F6 -> -22 | G7: =G5-G6 -> -25 | H7: =H5-H6 -> -178 | I7: =I5-I6 -> -230 | J7: =J5-J6 -> -32 | ... N7: =N5-N6 -> -45
B8: Incoming Shipments ⚠️ | C8: 0 | D8: 0 | E8: 0 | F8: 0 | G8: 0 | H8: 0 | I8: 0 | J8: 0 | K8: 0 | L8: 0 | M8: 0 | N8: 0
B9: Ending Inventory | C9: =MAX(0,C7+C8) -> 235 | D9: =MAX(0,D7+D8) -> 117 | E9: =MAX(0,E7+E8) -> 0 | F9: =MAX(0,F7+F8) -> 0 | G9: =MAX(0,G7+G8) -> 0 | H9: =MAX(0,H7+H8) -> 0 | I9: =MAX(0,I7+I8) -> 0 | J9: =MAX(0,J7+J8) -> 0 | ... N9: =MAX(0,N7+N8) -> 0 | O9: =IF(N9<Assumptions!G5,"🚨 REORDER NOW",IF(N9<1.5*Assumptions!G5,"⚠️ ORDER SOON","✅ OK")) -> 🚨 REORDER NOW
B10: Months of Supply | C10: =IFERROR(C9/D6,"-") -> 1.9915254 | D10: =IFERROR(D9/E6,"-") -> 0.68823529 | E10: =IFERROR(E9/F6,"-") -> 0 | F10: =IFERROR(F9/G6,"-") -> 0 | G10: =IFERROR(G9/H6,"-") -> 0 | H10: =IFERROR(H9/I6,"-") -> 0 | I10: =IFERROR(I9/J6,"-") -> 0 | J10: =IFERROR(J9/K6,"-") -> 0 | ... M10: =IFERROR(M9/N6,"-") -> 0 | N10: -
B11: 🚨 Order Alert | C11: {=IF(COLUMN()+Assumptions!F5>14,"",IF(INDIRECT(ADDRESS(ROW()-2,COLUMN()+Assumptions!F5))<Assumptions!G5,"ORDER NOW!",""))} -> ORDER NOW! | D11: {=IF(COLUMN()+Assumptions!F5>14,"",IF(INDIRECT(ADDRESS(ROW()-2,COLUMN()+Assumptions!F5))<Assumptions!G5,"ORDER NOW!",""))} -> ORDER NOW! | E11: {=IF(COLUMN()+Assumptions!F5>14,"",IF(INDIRECT(ADDRESS(ROW()-2,COLUMN()+Assumptions!F5))<Assumptions!G5,"ORDER NOW!",""))} -> ORDER NOW! | F11: {=IF(COLUMN()+Assumptions!F5>14,"",IF(INDIRECT(ADDRESS(ROW()-2,COLUMN()+Assumptions!F5))<Assumptions!G5,"ORDER NOW!",""))} -> ORDER NOW! | G11: {=IF(COLUMN()+Assumptions!F5>14,"",IF(INDIRECT(ADDRESS(ROW()-2,COLUMN()+Assumptions!F5))<Assumptions!G5,"ORDER NOW!",""))} -> ORDER NOW! | H11: {=IF(COLUMN()+Assumptions!F5>14,"",IF(INDIRECT(ADDRESS(ROW()-2,COLUMN()+Assumptions!F5))<Assumptions!G5,"ORDER NOW!",""))} -> ORDER NOW! | I11: {=IF(COLUMN()+Assumptions!F5>14,"",IF(INDIRECT(ADDRESS(ROW()-2,COLUMN()+Assumptions!F5))<Assumptions!G5,"ORDER NOW!",""))} -> ORDER NOW! | J11: {=IF(COLUMN()+Assumptions!F5>14,"",IF(INDIRECT(ADDRESS(ROW()-2,COLUMN()+Assumptions!F5))<Assumptions!G5,"ORDER NOW!",""))} -> ORDER NOW! | K11: {=IF(COLUMN()+Assumptions!F5>14,"",IF(INDIRECT(ADDRESS(ROW()-2,COLUMN()+Assumptions!F5))<Assumptions!G5,"ORDER NOW!",""))} -> ORDER NOW! | L11: {=IF(COLUMN()+Assumptions!F5>14,"",IF(INDIRECT(ADDRESS(ROW()-2,COLUMN()+Assumptions!F5))<Assumptions!G5,"ORDER NOW!",""))} | M11: {=IF(COLUMN()+Assumptions!F5>14,"",IF(INDIRECT(ADDRESS(ROW()-2,COLUMN()+Assumptions!F5))<Assumptions!G5,"ORDER NOW!",""))} | N11: {=IF(COLUMN()+Assumptions!F5>14,"",IF(INDIRECT(ADDRESS(ROW()-2,COLUMN()+Assumptions!F5))<Assumptions!G5,"ORDER NOW!",""))}
B12: Order Qty Needed | C12: {=IF(C11="ORDER NOW!",MAX(Assumptions!I5,Assumptions!G5-INDIRECT(ADDRESS(ROW()-3,COLUMN()+Assumptions!F5))+INDIRECT(ADDRESS(ROW()-6,COLUMN()+Assumptions!F5))),"")} -> 122 | D12: {=IF(D11="ORDER NOW!",MAX(Assumptions!I5,Assumptions!G5-INDIRECT(ADDRESS(ROW()-3,COLUMN()+Assumptions!F5))+INDIRECT(ADDRESS(ROW()-6,COLUMN()+Assumptions!F5))),"")} -> 125 | E12: {=IF(E11="ORDER NOW!",MAX(Assumptions!I5,Assumptions!G5-INDIRECT(ADDRESS(ROW()-3,COLUMN()+Assumptions!F5))+INDIRECT(ADDRESS(ROW()-6,COLUMN()+Assumptions!F5))),"")} -> 278 | F12: {=IF(F11="ORDER NOW!",MAX(Assumptions!I5,Assumptions!G5-INDIRECT(ADDRESS(ROW()-3,COLUMN()+Assumptions!F5))+INDIRECT(ADDRESS(ROW()-6,COLUMN()+Assumptions!F5))),"")} -> 330 | G12: {=IF(G11="ORDER NOW!",MAX(Assumptions!I5,Assumptions!G5-INDIRECT(ADDRESS(ROW()-3,COLUMN()+Assumptions!F5))+INDIRECT(ADDRESS(ROW()-6,COLUMN()+Assumptions!F5))),"")} -> 132 | H12: {=IF(H11="ORDER NOW!",MAX(Assumptions!I5,Assumptions!G5-INDIRECT(ADDRESS(ROW()-3,COLUMN()+Assumptions!F5))+INDIRECT(ADDRESS(ROW()-6,COLUMN()+Assumptions!F5))),"")} -> 135 | I12: {=IF(I11="ORDER NOW!",MAX(Assumptions!I5,Assumptions!G5-INDIRECT(ADDRESS(ROW()-3,COLUMN()+Assumptions!F5))+INDIRECT(ADDRESS(ROW()-6,COLUMN()+Assumptions!F5))),"")} -> 338 | J12: {=IF(J11="ORDER NOW!",MAX(Assumptions!I5,Assumptions!G5-INDIRECT(ADDRESS(ROW()-3,COLUMN()+Assumptions!F5))+INDIRECT(ADDRESS(ROW()-6,COLUMN()+Assumptions!F5))),"")} -> 390 | K12: {=IF(K11="ORDER NOW!",MAX(Assumptions!I5,Assumptions!G5-INDIRECT(ADDRESS(ROW()-3,COLUMN()+Assumptions!F5))+INDIRECT(ADDRESS(ROW()-6,COLUMN()+Assumptions!F5))),"")} -> 145 | L12: {=IF(L11="ORDER NOW!",MAX(Assumptions!I5,Assumptions!G5-INDIRECT(ADDRESS(ROW()-3,COLUMN()+Assumptions!F5))+INDIRECT(ADDRESS(ROW()-6,COLUMN()+Assumptions!F5))),"")} | M12: {=IF(M11="ORDER NOW!",MAX(Assumptions!I5,Assumptions!G5-INDIRECT(ADDRESS(ROW()-3,COLUMN()+Assumptions!F5))+INDIRECT(ADDRESS(ROW()-6,COLUMN()+Assumptions!F5))),"")} | N12: {=IF(N11="ORDER NOW!",MAX(Assumptions!I5,Assumptions!G5-INDIRECT(ADDRESS(ROW()-3,COLUMN()+Assumptions!F5))+INDIRECT(ADDRESS(ROW()-6,COLUMN()+Assumptions!F5))),"")}
A14: SKU002 | B14: Beginning Inventory | C14: =Assumptions!H6 -> 180 | D14: =C18 -> 168 | E14: =D18 -> 79 | F14: =E18 -> 0 | G14: =F18 -> 0 | H14: =G18 -> 0 | I14: =H18 -> 0 | J14: =I18 -> 0 | K14: =J18 -> 0 | ... N14: =M18 -> 0
B15: Gross Sales | C15: ='Demand Forecast'!C41 -> 12 | D15: ='Demand Forecast'!D41 -> 89 | E15: ='Demand Forecast'!E41 -> 116 | F15: ='Demand Forecast'!F41 -> 18 | G15: ='Demand Forecast'!G41 -> 20 | H15: ='Demand Forecast'!H41 -> 122 | I15: ='Demand Forecast'!I41 -> 174 | J15: ='Demand Forecast'!J41 -> 26 | ... N15: ='Demand Forecast'!N41 -> 35
B16: Net Position | C16: =C14-C15 -> 168 | D16: =D14-D15 -> 79 | E16: =E14-E15 -> -37 | F16: =F14-F15 -> -18 | G16: =G14-G15 -> -20 | H16: =H14-H15 -> -122 | I16: =I14-I15 -> -174 | J16: =J14-J15 -> -26 | ... N16: =N14-N15 -> -35
B17: Incoming Shipments ⚠️ | C17: 0 | D17: 0 | E17: 0 | F17: 0 | G17: 0 | H17: 0 | I17: 0 | J17: 0 | K17: 0 | L17: 0 | M17: 0 | N17: 0
B18: Ending Inventory | C18: =MAX(0,C16+C17) -> 168 | D18: =MAX(0,D16+D17) -> 79 | E18: =MAX(0,E16+E17) -> 0 | F18: =MAX(0,F16+F17) -> 0 | G18: =MAX(0,G16+G17) -> 0 | H18: =MAX(0,H16+H17) -> 0 | I18: =MAX(0,I16+I17) -> 0 | J18: =MAX(0,J16+J17) -> 0 | ... N18: =MAX(0,N16+N17) -> 0 | O18: =IF(N18<Assumptions!G6,"🚨 REORDER NOW",IF(N18<1.5*Assumptions!G6,"⚠️ ORDER SOON","✅ OK")) -> 🚨 REORDER NOW
B19: Months of Supply | C19: =IFERROR(C18/D15,"-") -> 1.8876404 | D19: =IFERROR(D18/E15,"-") -> 0.68103448 | E19: =IFERROR(E18/F15,"-") -> 0 | F19: =IFERROR(F18/G15,"-") -> 0 | G19: =IFERROR(G18/H15,"-") -> 0 | H19: =IFERROR(H18/I15,"-") -> 0 | I19: =IFERROR(I18/J15,"-") -> 0 | J19: =IFERROR(J18/K15,"-") -> 0 | ... M19: =IFERROR(M18/N15,"-") -> 0 | N19: -
B20: 🚨 Order Alert | C20: {=IF(COLUMN()+Assumptions!F6>14,"",IF(INDIRECT(ADDRESS(ROW()-2,COLUMN()+Assumptions!F6))<Assumptions!G6,"ORDER NOW!",""))} -> ORDER NOW! | D20: {=IF(COLUMN()+Assumptions!F6>14,"",IF(INDIRECT(ADDRESS(ROW()-2,COLUMN()+Assumptions!F6))<Assumptions!G6,"ORDER NOW!",""))} -> ORDER NOW! | E20: {=IF(COLUMN()+Assumptions!F6>14,"",IF(INDIRECT(ADDRESS(ROW()-2,COLUMN()+Assumptions!F6))<Assumptions!G6,"ORDER NOW!",""))} -> ORDER NOW! | F20: {=IF(COLUMN()+Assumptions!F6>14,"",IF(INDIRECT(ADDRESS(ROW()-2,COLUMN()+Assumptions!F6))<Assumptions!G6,"ORDER NOW!",""))} -> ORDER NOW! | G20: {=IF(COLUMN()+Assumptions!F6>14,"",IF(INDIRECT(ADDRESS(ROW()-2,COLUMN()+Assumptions!F6))<Assumptions!G6,"ORDER NOW!",""))} -> ORDER NOW! | H20: {=IF(COLUMN()+Assumptions!F6>14,"",IF(INDIRECT(ADDRESS(ROW()-2,COLUMN()+Assumptions!F6))<Assumptions!G6,"ORDER NOW!",""))} -> ORDER NOW! | I20: {=IF(COLUMN()+Assumptions!F6>14,"",IF(INDIRECT(ADDRESS(ROW()-2,COLUMN()+Assumptions!F6))<Assumptions!G6,"ORDER NOW!",""))} -> ORDER NOW! | J20: {=IF(COLUMN()+Assumptions!F6>14,"",IF(INDIRECT(ADDRESS(ROW()-2,COLUMN()+Assumptions!F6))<Assumptions!G6,"ORDER NOW!",""))} -> ORDER NOW! | K20: {=IF(COLUMN()+Assumptions!F6>14,"",IF(INDIRECT(ADDRESS(ROW()-2,COLUMN()+Assumptions!F6))<Assumptions!G6,"ORDER NOW!",""))} -> ORDER NOW! | L20: {=IF(COLUMN()+Assumptions!F6>14,"",IF(INDIRECT(ADDRESS(ROW()-2,COLUMN()+Assumptions!F6))<Assumptions!G6,"ORDER NOW!",""))} | M20: {=IF(COLUMN()+Assumptions!F6>14,"",IF(INDIRECT(ADDRESS(ROW()-2,COLUMN()+Assumptions!F6))<Assumptions!G6,"ORDER NOW!",""))} | N20: {=IF(COLUMN()+Assumptions!F6>14,"",IF(INDIRECT(ADDRESS(ROW()-2,COLUMN()+Assumptions!F6))<Assumptions!G6,"ORDER NOW!",""))}
B21: Order Qty Needed | C21: {=IF(C20="ORDER NOW!",MAX(Assumptions!I6,Assumptions!G6-INDIRECT(ADDRESS(ROW()-3,COLUMN()+Assumptions!F6))+INDIRECT(ADDRESS(ROW()-6,COLUMN()+Assumptions!F6))),"")} -> 118 | D21: {=IF(D20="ORDER NOW!",MAX(Assumptions!I6,Assumptions!G6-INDIRECT(ADDRESS(ROW()-3,COLUMN()+Assumptions!F6))+INDIRECT(ADDRESS(ROW()-6,COLUMN()+Assumptions!F6))),"")} -> 120 | E21: {=IF(E20="ORDER NOW!",MAX(Assumptions!I6,Assumptions!G6-INDIRECT(ADDRESS(ROW()-3,COLUMN()+Assumptions!F6))+INDIRECT(ADDRESS(ROW()-6,COLUMN()+Assumptions!F6))),"")} -> 222 | F21: {=IF(F20="ORDER NOW!",MAX(Assumptions!I6,Assumptions!G6-INDIRECT(ADDRESS(ROW()-3,COLUMN()+Assumptions!F6))+INDIRECT(ADDRESS(ROW()-6,COLUMN()+Assumptions!F6))),"")} -> 274 | G21: {=IF(G20="ORDER NOW!",MAX(Assumptions!I6,Assumptions!G6-INDIRECT(ADDRESS(ROW()-3,COLUMN()+Assumptions!F6))+INDIRECT(ADDRESS(ROW()-6,COLUMN()+Assumptions!F6))),"")} -> 126 | H21: {=IF(H20="ORDER NOW!",MAX(Assumptions!I6,Assumptions!G6-INDIRECT(ADDRESS(ROW()-3,COLUMN()+Assumptions!F6))+INDIRECT(ADDRESS(ROW()-6,COLUMN()+Assumptions!F6))),"")} -> 128 | I21: {=IF(I20="ORDER NOW!",MAX(Assumptions!I6,Assumptions!G6-INDIRECT(ADDRESS(ROW()-3,COLUMN()+Assumptions!F6))+INDIRECT(ADDRESS(ROW()-6,COLUMN()+Assumptions!F6))),"")} -> 255 | J21: {=IF(J20="ORDER NOW!",MAX(Assumptions!I6,Assumptions!G6-INDIRECT(ADDRESS(ROW()-3,COLUMN()+Assumptions!F6))+INDIRECT(ADDRESS(ROW()-6,COLUMN()+Assumptions!F6))),"")} -> 332 | K21: {=IF(K20="ORDER NOW!",MAX(Assumptions!I6,Assumptions!G6-INDIRECT(ADDRESS(ROW()-3,COLUMN()+Assumptions!F6))+INDIRECT(ADDRESS(ROW()-6,COLUMN()+Assumptions!F6))),"")} -> 135 | L21: {=IF(L20="ORDER NOW!",MAX(Assumptions!I6,Assumptions!G6-INDIRECT(ADDRESS(ROW()-3,COLUMN()+Assumptions!F6))+INDIRECT(ADDRESS(ROW()-6,COLUMN()+Assumptions!F6))),"")} | M21: {=IF(M20="ORDER NOW!",MAX(Assumptions!I6,Assumptions!G6-INDIRECT(ADDRESS(ROW()-3,COLUMN()+Assumptions!F6))+INDIRECT(ADDRESS(ROW()-6,COLUMN()+Assumptions!F6))),"")} | N21: {=IF(N20="ORDER NOW!",MAX(Assumptions!I6,Assumptions!G6-INDIRECT(ADDRESS(ROW()-3,COLUMN()+Assumptions!F6))+INDIRECT(ADDRESS(ROW()-6,COLUMN()+Assumptions!F6))),"")}
A23: SKU003 | B23: Beginning Inventory | C23: =Assumptions!H7 -> 150 | D23: =C27 -> 140 | E23: =D27 -> 68 | F23: =E27 -> 0 | G23: =F27 -> 0 | H23: =G27 -> 0 | I23: =H27 -> 0 | J23: =I27 -> 0 | K23: =J27 -> 0 | ... N23: =M27 -> 0
B24: Gross Sales | C24: ='Demand Forecast'!C42 -> 10 | D24: ='Demand Forecast'!D42 -> 72 | E24: ='Demand Forecast'!E42 -> 94 | F24: ='Demand Forecast'!F42 -> 15 | G24: ='Demand Forecast'!G42 -> 17 | H24: ='Demand Forecast'!H42 -> 99 | I24: ='Demand Forecast'!I42 -> 141 | J24: ='Demand Forecast'!J42 -> 23 | ... N24: ='Demand Forecast'!N42 -> 32
B25: Net Position | C25: =C23-C24 -> 140 | D25: =D23-D24 -> 68 | E25: =E23-E24 -> -26 | F25: =F23-F24 -> -15 | G25: =G23-G24 -> -17 | H25: =H23-H24 -> -99 | I25: =I23-I24 -> -141 | J25: =J23-J24 -> -23 | ... N25: =N23-N24 -> -32
B26: Incoming Shipments ⚠️ | C26: 0 | D26: 0 | E26: 0 | F26: 0 | G26: 0 | H26: 0 | I26: 0 | J26: 0 | K26: 0 | L26: 0 | M26: 0 | N26: 0
B27: Ending Inventory | C27: =MAX(0,C25+C26) -> 140 | D27: =MAX(0,D25+D26) -> 68 | E27: =MAX(0,E25+E26) -> 0 | F27: =MAX(0,F25+F26) -> 0 | G27: =MAX(0,G25+G26) -> 0 | H27: =MAX(0,H25+H26) -> 0 | I27: =MAX(0,I25+I26) -> 0 | J27: =MAX(0,J25+J26) -> 0 | ... N27: =MAX(0,N25+N26) -> 0 | O27: =IF(N27<Assumptions!G7,"🚨 REORDER NOW",IF(N27<1.5*Assumptions!G7,"⚠️ ORDER SOON","✅ OK")) -> 🚨 REORDER NOW
B28: Months of Supply | C28: =IFERROR(C27/D24,"-") -> 1.9444444 | D28: =IFERROR(D27/E24,"-") -> 0.72340426 | E28: =IFERROR(E27/F24,"-") -> 0 | F28: =IFERROR(F27/G24,"-") -> 0 | G28: =IFERROR(G27/H24,"-") -> 0 | H28: =IFERROR(H27/I24,"-") -> 0 | I28: =IFERROR(I27/J24,"-") -> 0 | J28: =IFERROR(J27/K24,"-") -> 0 | ... M28: =IFERROR(M27/N24,"-") -> 0 | N28: -
B29: 🚨 Order Alert | C29: {=IF(COLUMN()+Assumptions!F7>14,"",IF(INDIRECT(ADDRESS(ROW()-2,COLUMN()+Assumptions!F7))<Assumptions!G7,"ORDER NOW!",""))} -> ORDER NOW! | D29: {=IF(COLUMN()+Assumptions!F7>14,"",IF(INDIRECT(ADDRESS(ROW()-2,COLUMN()+Assumptions!F7))<Assumptions!G7,"ORDER NOW!",""))} -> ORDER NOW! | E29: {=IF(COLUMN()+Assumptions!F7>14,"",IF(INDIRECT(ADDRESS(ROW()-2,COLUMN()+Assumptions!F7))<Assumptions!G7,"ORDER NOW!",""))} -> ORDER NOW! | F29: {=IF(COLUMN()+Assumptions!F7>14,"",IF(INDIRECT(ADDRESS(ROW()-2,COLUMN()+Assumptions!F7))<Assumptions!G7,"ORDER NOW!",""))} -> ORDER NOW! | G29: {=IF(COLUMN()+Assumptions!F7>14,"",IF(INDIRECT(ADDRESS(ROW()-2,COLUMN()+Assumptions!F7))<Assumptions!G7,"ORDER NOW!",""))} -> ORDER NOW! | H29: {=IF(COLUMN()+Assumptions!F7>14,"",IF(INDIRECT(ADDRESS(ROW()-2,COLUMN()+Assumptions!F7))<Assumptions!G7,"ORDER NOW!",""))} -> ORDER NOW! | I29: {=IF(COLUMN()+Assumptions!F7>14,"",IF(INDIRECT(ADDRESS(ROW()-2,COLUMN()+Assumptions!F7))<Assumptions!G7,"ORDER NOW!",""))} -> ORDER NOW! | J29: {=IF(COLUMN()+Assumptions!F7>14,"",IF(INDIRECT(ADDRESS(ROW()-2,COLUMN()+Assumptions!F7))<Assumptions!G7,"ORDER NOW!",""))} -> ORDER NOW! | K29: {=IF(COLUMN()+Assumptions!F7>14,"",IF(INDIRECT(ADDRESS(ROW()-2,COLUMN()+Assumptions!F7))<Assumptions!G7,"ORDER NOW!",""))} -> ORDER NOW! | L29: {=IF(COLUMN()+Assumptions!F7>14,"",IF(INDIRECT(ADDRESS(ROW()-2,COLUMN()+Assumptions!F7))<Assumptions!G7,"ORDER NOW!",""))} | M29: {=IF(COLUMN()+Assumptions!F7>14,"",IF(INDIRECT(ADDRESS(ROW()-2,COLUMN()+Assumptions!F7))<Assumptions!G7,"ORDER NOW!",""))} | N29: {=IF(COLUMN()+Assumptions!F7>14,"",IF(INDIRECT(ADDRESS(ROW()-2,COLUMN()+Assumptions!F7))<Assumptions!G7,"ORDER NOW!",""))}
B30: Order Qty Needed | C30: {=IF(C29="ORDER NOW!",MAX(Assumptions!I7,Assumptions!G7-INDIRECT(ADDRESS(ROW()-3,COLUMN()+Assumptions!F7))+INDIRECT(ADDRESS(ROW()-6,COLUMN()+Assumptions!F7))),"")} -> 95 | D30: {=IF(D29="ORDER NOW!",MAX(Assumptions!I7,Assumptions!G7-INDIRECT(ADDRESS(ROW()-3,COLUMN()+Assumptions!F7))+INDIRECT(ADDRESS(ROW()-6,COLUMN()+Assumptions!F7))),"")} -> 97 | E30: {=IF(E29="ORDER NOW!",MAX(Assumptions!I7,Assumptions!G7-INDIRECT(ADDRESS(ROW()-3,COLUMN()+Assumptions!F7))+INDIRECT(ADDRESS(ROW()-6,COLUMN()+Assumptions!F7))),"")} -> 179 | F30: {=IF(F29="ORDER NOW!",MAX(Assumptions!I7,Assumptions!G7-INDIRECT(ADDRESS(ROW()-3,COLUMN()+Assumptions!F7))+INDIRECT(ADDRESS(ROW()-6,COLUMN()+Assumptions!F7))),"")} -> 221 | G30: {=IF(G29="ORDER NOW!",MAX(Assumptions!I7,Assumptions!G7-INDIRECT(ADDRESS(ROW()-3,COLUMN()+Assumptions!F7))+INDIRECT(ADDRESS(ROW()-6,COLUMN()+Assumptions!F7))),"")} -> 103 | H30: {=IF(H29="ORDER NOW!",MAX(Assumptions!I7,Assumptions!G7-INDIRECT(ADDRESS(ROW()-3,COLUMN()+Assumptions!F7))+INDIRECT(ADDRESS(ROW()-6,COLUMN()+Assumptions!F7))),"")} -> 105 | I30: {=IF(I29="ORDER NOW!",MAX(Assumptions!I7,Assumptions!G7-INDIRECT(ADDRESS(ROW()-3,COLUMN()+Assumptions!F7))+INDIRECT(ADDRESS(ROW()-6,COLUMN()+Assumptions!F7))),"")} -> 207 | J30: {=IF(J29="ORDER NOW!",MAX(Assumptions!I7,Assumptions!G7-INDIRECT(ADDRESS(ROW()-3,COLUMN()+Assumptions!F7))+INDIRECT(ADDRESS(ROW()-6,COLUMN()+Assumptions!F7))),"")} -> 259 | K30: {=IF(K29="ORDER NOW!",MAX(Assumptions!I7,Assumptions!G7-INDIRECT(ADDRESS(ROW()-3,COLUMN()+Assumptions!F7))+INDIRECT(ADDRESS(ROW()-6,COLUMN()+Assumptions!F7))),"")} -> 112 | L30: {=IF(L29="ORDER NOW!",MAX(Assumptions!I7,Assumptions!G7-INDIRECT(ADDRESS(ROW()-3,COLUMN()+Assumptions!F7))+INDIRECT(ADDRESS(ROW()-6,COLUMN()+Assumptions!F7))),"")} | M30: {=IF(M29="ORDER NOW!",MAX(Assumptions!I7,Assumptions!G7-INDIRECT(ADDRESS(ROW()-3,COLUMN()+Assumptions!F7))+INDIRECT(ADDRESS(ROW()-6,COLUMN()+Assumptions!F7))),"")} | N30: {=IF(N29="ORDER NOW!",MAX(Assumptions!I7,Assumptions!G7-INDIRECT(ADDRESS(ROW()-3,COLUMN()+Assumptions!F7))+INDIRECT(ADDRESS(ROW()-6,COLUMN()+Assumptions!F7))),"")}
A32: SKU004 | B32: Beginning Inventory | C32: =Assumptions!H8 -> 120 | D32: =C36 -> 112 | E32: =D36 -> 62 | F32: =E36 -> 1 | G32: =F36 -> 0 | H32: =G36 -> 0 | I32: =H36 -> 0 | J32: =I36 -> 0 | K32: =J36 -> 0 | ... N32: =M36 -> 0
B33: Gross Sales | C33: ='Demand Forecast'!C43 -> 8 | D33: ='Demand Forecast'!D43 -> 50 | E33: ='Demand Forecast'!E43 -> 61 | F33: ='Demand Forecast'!F43 -> 13 | G33: ='Demand Forecast'!G43 -> 15 | H33: ='Demand Forecast'!H43 -> 77 | I33: ='Demand Forecast'!I43 -> 99 | J33: ='Demand Forecast'!J43 -> 21 | ... N33: ='Demand Forecast'!N43 -> 30
B34: Net Position | C34: =C32-C33 -> 112 | D34: =D32-D33 -> 62 | E34: =E32-E33 -> 1 | F34: =F32-F33 -> -12 | G34: =G32-G33 -> -15 | H34: =H32-H33 -> -77 | I34: =I32-I33 -> -99 | J34: =J32-J33 -> -21 | ... N34: =N32-N33 -> -30
B35: Incoming Shipments ⚠️ | C35: 0 | D35: 0 | E35: 0 | F35: 0 | G35: 0 | H35: 0 | I35: 0 | J35: 0 | K35: 0 | L35: 0 | M35: 0 | N35: 0
B36: Ending Inventory | C36: =MAX(0,C34+C35) -> 112 | D36: =MAX(0,D34+D35) -> 62 | E36: =MAX(0,E34+E35) -> 1 | F36: =MAX(0,F34+F35) -> 0 | G36: =MAX(0,G34+G35) -> 0 | H36: =MAX(0,H34+H35) -> 0 | I36: =MAX(0,I34+I35) -> 0 | J36: =MAX(0,J34+J35) -> 0 | ... N36: =MAX(0,N34+N35) -> 0 | O36: =IF(N36<Assumptions!G8,"🚨 REORDER NOW",IF(N36<1.5*Assumptions!G8,"⚠️ ORDER SOON","✅ OK")) -> 🚨 REORDER NOW
B37: Months of Supply | C37: =IFERROR(C36/D33,"-") -> 2.24 | D37: =IFERROR(D36/E33,"-") -> 1.0163934 | E37: =IFERROR(E36/F33,"-") -> 0.076923077 | F37: =IFERROR(F36/G33,"-") -> 0 | G37: =IFERROR(G36/H33,"-") -> 0 | H37: =IFERROR(H36/I33,"-") -> 0 | I37: =IFERROR(I36/J33,"-") -> 0 | J37: =IFERROR(J36/K33,"-") -> 0 | ... M37: =IFERROR(M36/N33,"-") -> 0 | N37: -
B38: 🚨 Order Alert | C38: {=IF(COLUMN()+Assumptions!F8>14,"",IF(INDIRECT(ADDRESS(ROW()-2,COLUMN()+Assumptions!F8))<Assumptions!G8,"ORDER NOW!",""))} -> ORDER NOW! | D38: {=IF(COLUMN()+Assumptions!F8>14,"",IF(INDIRECT(ADDRESS(ROW()-2,COLUMN()+Assumptions!F8))<Assumptions!G8,"ORDER NOW!",""))} -> ORDER NOW! | E38: {=IF(COLUMN()+Assumptions!F8>14,"",IF(INDIRECT(ADDRESS(ROW()-2,COLUMN()+Assumptions!F8))<Assumptions!G8,"ORDER NOW!",""))} -> ORDER NOW! | F38: {=IF(COLUMN()+Assumptions!F8>14,"",IF(INDIRECT(ADDRESS(ROW()-2,COLUMN()+Assumptions!F8))<Assumptions!G8,"ORDER NOW!",""))} -> ORDER NOW! | G38: {=IF(COLUMN()+Assumptions!F8>14,"",IF(INDIRECT(ADDRESS(ROW()-2,COLUMN()+Assumptions!F8))<Assumptions!G8,"ORDER NOW!",""))} -> ORDER NOW! | H38: {=IF(COLUMN()+Assumptions!F8>14,"",IF(INDIRECT(ADDRESS(ROW()-2,COLUMN()+Assumptions!F8))<Assumptions!G8,"ORDER NOW!",""))} -> ORDER NOW! | I38: {=IF(COLUMN()+Assumptions!F8>14,"",IF(INDIRECT(ADDRESS(ROW()-2,COLUMN()+Assumptions!F8))<Assumptions!G8,"ORDER NOW!",""))} -> ORDER NOW! | J38: {=IF(COLUMN()+Assumptions!F8>14,"",IF(INDIRECT(ADDRESS(ROW()-2,COLUMN()+Assumptions!F8))<Assumptions!G8,"ORDER NOW!",""))} -> ORDER NOW! | K38: {=IF(COLUMN()+Assumptions!F8>14,"",IF(INDIRECT(ADDRESS(ROW()-2,COLUMN()+Assumptions!F8))<Assumptions!G8,"ORDER NOW!",""))} -> ORDER NOW! | L38: {=IF(COLUMN()+Assumptions!F8>14,"",IF(INDIRECT(ADDRESS(ROW()-2,COLUMN()+Assumptions!F8))<Assumptions!G8,"ORDER NOW!",""))} | M38: {=IF(COLUMN()+Assumptions!F8>14,"",IF(INDIRECT(ADDRESS(ROW()-2,COLUMN()+Assumptions!F8))<Assumptions!G8,"ORDER NOW!",""))} | N38: {=IF(COLUMN()+Assumptions!F8>14,"",IF(INDIRECT(ADDRESS(ROW()-2,COLUMN()+Assumptions!F8))<Assumptions!G8,"ORDER NOW!",""))}
B39: Order Qty Needed | C39: {=IF(C38="ORDER NOW!",MAX(Assumptions!I8,Assumptions!G8-INDIRECT(ADDRESS(ROW()-3,COLUMN()+Assumptions!F8))+INDIRECT(ADDRESS(ROW()-6,COLUMN()+Assumptions!F8))),"")} -> 93 | D39: {=IF(D38="ORDER NOW!",MAX(Assumptions!I8,Assumptions!G8-INDIRECT(ADDRESS(ROW()-3,COLUMN()+Assumptions!F8))+INDIRECT(ADDRESS(ROW()-6,COLUMN()+Assumptions!F8))),"")} -> 95 | E39: {=IF(E38="ORDER NOW!",MAX(Assumptions!I8,Assumptions!G8-INDIRECT(ADDRESS(ROW()-3,COLUMN()+Assumptions!F8))+INDIRECT(ADDRESS(ROW()-6,COLUMN()+Assumptions!F8))),"")} -> 157 | F39: {=IF(F38="ORDER NOW!",MAX(Assumptions!I8,Assumptions!G8-INDIRECT(ADDRESS(ROW()-3,COLUMN()+Assumptions!F8))+INDIRECT(ADDRESS(ROW()-6,COLUMN()+Assumptions!F8))),"")} -> 179 | G39: {=IF(G38="ORDER NOW!",MAX(Assumptions!I8,Assumptions!G8-INDIRECT(ADDRESS(ROW()-3,COLUMN()+Assumptions!F8))+INDIRECT(ADDRESS(ROW()-6,COLUMN()+Assumptions!F8))),"")} -> 101 | H39: {=IF(H38="ORDER NOW!",MAX(Assumptions!I8,Assumptions!G8-INDIRECT(ADDRESS(ROW()-3,COLUMN()+Assumptions!F8))+INDIRECT(ADDRESS(ROW()-6,COLUMN()+Assumptions!F8))),"")} -> 103 | I39: {=IF(I38="ORDER NOW!",MAX(Assumptions!I8,Assumptions!G8-INDIRECT(ADDRESS(ROW()-3,COLUMN()+Assumptions!F8))+INDIRECT(ADDRESS(ROW()-6,COLUMN()+Assumptions!F8))),"")} -> 180 | J39: {=IF(J38="ORDER NOW!",MAX(Assumptions!I8,Assumptions!G8-INDIRECT(ADDRESS(ROW()-3,COLUMN()+Assumptions!F8))+INDIRECT(ADDRESS(ROW()-6,COLUMN()+Assumptions!F8))),"")} -> 207 | K39: {=IF(K38="ORDER NOW!",MAX(Assumptions!I8,Assumptions!G8-INDIRECT(ADDRESS(ROW()-3,COLUMN()+Assumptions!F8))+INDIRECT(ADDRESS(ROW()-6,COLUMN()+Assumptions!F8))),"")} -> 110 | L39: {=IF(L38="ORDER NOW!",MAX(Assumptions!I8,Assumptions!G8-INDIRECT(ADDRESS(ROW()-3,COLUMN()+Assumptions!F8))+INDIRECT(ADDRESS(ROW()-6,COLUMN()+Assumptions!F8))),"")} | M39: {=IF(M38="ORDER NOW!",MAX(Assumptions!I8,Assumptions!G8-INDIRECT(ADDRESS(ROW()-3,COLUMN()+Assumptions!F8))+INDIRECT(ADDRESS(ROW()-6,COLUMN()+Assumptions!F8))),"")} | N39: {=IF(N38="ORDER NOW!",MAX(Assumptions!I8,Assumptions!G8-INDIRECT(ADDRESS(ROW()-3,COLUMN()+Assumptions!F8))+INDIRECT(ADDRESS(ROW()-6,COLUMN()+Assumptions!F8))),"")}
A41: SKU005 | B41: Beginning Inventory | C41: =Assumptions!H9 -> 110 | D41: =C45 -> 103 | E41: =D45 -> 59 | F41: =E45 -> 9 | G41: =F45 -> 0 | H41: =G45 -> 0 | I41: =H45 -> 0 | J41: =I45 -> 0 | K41: =J45 -> 0 | ... N41: =M45 -> 0
B42: Gross Sales | C42: ='Demand Forecast'!C44 -> 7 | D42: ='Demand Forecast'!D44 -> 44 | E42: ='Demand Forecast'!E44 -> 50 | F42: ='Demand Forecast'!F44 -> 12 | G42: ='Demand Forecast'!G44 -> 14 | H42: ='Demand Forecast'!H44 -> 71 | I42: ='Demand Forecast'!I44 -> 88 | J42: ='Demand Forecast'!J44 -> 20 | ... N42: ='Demand Forecast'!N44 -> 28
B43: Net Position | C43: =C41-C42 -> 103 | D43: =D41-D42 -> 59 | E43: =E41-E42 -> 9 | F43: =F41-F42 -> -3 | G43: =G41-G42 -> -14 | H43: =H41-H42 -> -71 | I43: =I41-I42 -> -88 | J43: =J41-J42 -> -20 | ... N43: =N41-N42 -> -28
B44: Incoming Shipments ⚠️ | C44: 0 | D44: 0 | E44: 0 | F44: 0 | G44: 0 | H44: 0 | I44: 0 | J44: 0 | K44: 0 | L44: 0 | M44: 0 | N44: 0
B45: Ending Inventory | C45: =MAX(0,C43+C44) -> 103 | D45: =MAX(0,D43+D44) -> 59 | E45: =MAX(0,E43+E44) -> 9 | F45: =MAX(0,F43+F44) -> 0 | G45: =MAX(0,G43+G44) -> 0 | H45: =MAX(0,H43+H44) -> 0 | I45: =MAX(0,I43+I44) -> 0 | J45: =MAX(0,J43+J44) -> 0 | ... N45: =MAX(0,N43+N44) -> 0 | O45: =IF(N45<Assumptions!G9,"🚨 REORDER NOW",IF(N45<1.5*Assumptions!G9,"⚠️ ORDER SOON","✅ OK")) -> 🚨 REORDER NOW
B46: Months of Supply | C46: =IFERROR(C45/D42,"-") -> 2.3409091 | D46: =IFERROR(D45/E42,"-") -> 1.18 | E46: =IFERROR(E45/F42,"-") -> 0.75 | F46: =IFERROR(F45/G42,"-") -> 0 | G46: =IFERROR(G45/H42,"-") -> 0 | H46: =IFERROR(H45/I42,"-") -> 0 | I46: =IFERROR(I45/J42,"-") -> 0 | J46: =IFERROR(J45/K42,"-") -> 0 | ... M46: =IFERROR(M45/N42,"-") -> 0 | N46: -
B47: 🚨 Order Alert | C47: {=IF(COLUMN()+Assumptions!F9>14,"",IF(INDIRECT(ADDRESS(ROW()-2,COLUMN()+Assumptions!F9))<Assumptions!G9,"ORDER NOW!",""))} -> ORDER NOW! | D47: {=IF(COLUMN()+Assumptions!F9>14,"",IF(INDIRECT(ADDRESS(ROW()-2,COLUMN()+Assumptions!F9))<Assumptions!G9,"ORDER NOW!",""))} -> ORDER NOW! | E47: {=IF(COLUMN()+Assumptions!F9>14,"",IF(INDIRECT(ADDRESS(ROW()-2,COLUMN()+Assumptions!F9))<Assumptions!G9,"ORDER NOW!",""))} -> ORDER NOW! | F47: {=IF(COLUMN()+Assumptions!F9>14,"",IF(INDIRECT(ADDRESS(ROW()-2,COLUMN()+Assumptions!F9))<Assumptions!G9,"ORDER NOW!",""))} -> ORDER NOW! | G47: {=IF(COLUMN()+Assumptions!F9>14,"",IF(INDIRECT(ADDRESS(ROW()-2,COLUMN()+Assumptions!F9))<Assumptions!G9,"ORDER NOW!",""))} -> ORDER NOW! | H47: {=IF(COLUMN()+Assumptions!F9>14,"",IF(INDIRECT(ADDRESS(ROW()-2,COLUMN()+Assumptions!F9))<Assumptions!G9,"ORDER NOW!",""))} -> ORDER NOW! | I47: {=IF(COLUMN()+Assumptions!F9>14,"",IF(INDIRECT(ADDRESS(ROW()-2,COLUMN()+Assumptions!F9))<Assumptions!G9,"ORDER NOW!",""))} -> ORDER NOW! | J47: {=IF(COLUMN()+Assumptions!F9>14,"",IF(INDIRECT(ADDRESS(ROW()-2,COLUMN()+Assumptions!F9))<Assumptions!G9,"ORDER NOW!",""))} -> ORDER NOW! | K47: {=IF(COLUMN()+Assumptions!F9>14,"",IF(INDIRECT(ADDRESS(ROW()-2,COLUMN()+Assumptions!F9))<Assumptions!G9,"ORDER NOW!",""))} -> ORDER NOW! | L47: {=IF(COLUMN()+Assumptions!F9>14,"",IF(INDIRECT(ADDRESS(ROW()-2,COLUMN()+Assumptions!F9))<Assumptions!G9,"ORDER NOW!",""))} | M47: {=IF(COLUMN()+Assumptions!F9>14,"",IF(INDIRECT(ADDRESS(ROW()-2,COLUMN()+Assumptions!F9))<Assumptions!G9,"ORDER NOW!",""))} | N47: {=IF(COLUMN()+Assumptions!F9>14,"",IF(INDIRECT(ADDRESS(ROW()-2,COLUMN()+Assumptions!F9))<Assumptions!G9,"ORDER NOW!",""))}
B48: Order Qty Needed | C48: {=IF(C47="ORDER NOW!",MAX(Assumptions!I9,Assumptions!G9-INDIRECT(ADDRESS(ROW()-3,COLUMN()+Assumptions!F9))+INDIRECT(ADDRESS(ROW()-6,COLUMN()+Assumptions!F9))),"")} -> 92 | D48: {=IF(D47="ORDER NOW!",MAX(Assumptions!I9,Assumptions!G9-INDIRECT(ADDRESS(ROW()-3,COLUMN()+Assumptions!F9))+INDIRECT(ADDRESS(ROW()-6,COLUMN()+Assumptions!F9))),"")} -> 94 | E48: {=IF(E47="ORDER NOW!",MAX(Assumptions!I9,Assumptions!G9-INDIRECT(ADDRESS(ROW()-3,COLUMN()+Assumptions!F9))+INDIRECT(ADDRESS(ROW()-6,COLUMN()+Assumptions!F9))),"")} -> 151 | F48: {=IF(F47="ORDER NOW!",MAX(Assumptions!I9,Assumptions!G9-INDIRECT(ADDRESS(ROW()-3,COLUMN()+Assumptions!F9))+INDIRECT(ADDRESS(ROW()-6,COLUMN()+Assumptions!F9))),"")} -> 168 | G48: {=IF(G47="ORDER NOW!",MAX(Assumptions!I9,Assumptions!G9-INDIRECT(ADDRESS(ROW()-3,COLUMN()+Assumptions!F9))+INDIRECT(ADDRESS(ROW()-6,COLUMN()+Assumptions!F9))),"")} -> 100 | H48: {=IF(H47="ORDER NOW!",MAX(Assumptions!I9,Assumptions!G9-INDIRECT(ADDRESS(ROW()-3,COLUMN()+Assumptions!F9))+INDIRECT(ADDRESS(ROW()-6,COLUMN()+Assumptions!F9))),"")} -> 102 | I48: {=IF(I47="ORDER NOW!",MAX(Assumptions!I9,Assumptions!G9-INDIRECT(ADDRESS(ROW()-3,COLUMN()+Assumptions!F9))+INDIRECT(ADDRESS(ROW()-6,COLUMN()+Assumptions!F9))),"")} -> 174 | J48: {=IF(J47="ORDER NOW!",MAX(Assumptions!I9,Assumptions!G9-INDIRECT(ADDRESS(ROW()-3,COLUMN()+Assumptions!F9))+INDIRECT(ADDRESS(ROW()-6,COLUMN()+Assumptions!F9))),"")} -> 196 | K48: {=IF(K47="ORDER NOW!",MAX(Assumptions!I9,Assumptions!G9-INDIRECT(ADDRESS(ROW()-3,COLUMN()+Assumptions!F9))+INDIRECT(ADDRESS(ROW()-6,COLUMN()+Assumptions!F9))),"")} -> 108 | L48: {=IF(L47="ORDER NOW!",MAX(Assumptions!I9,Assumptions!G9-INDIRECT(ADDRESS(ROW()-3,COLUMN()+Assumptions!F9))+INDIRECT(ADDRESS(ROW()-6,COLUMN()+Assumptions!F9))),"")} | M48: {=IF(M47="ORDER NOW!",MAX(Assumptions!I9,Assumptions!G9-INDIRECT(ADDRESS(ROW()-3,COLUMN()+Assumptions!F9))+INDIRECT(ADDRESS(ROW()-6,COLUMN()+Assumptions!F9))),"")} | N48: {=IF(N47="ORDER NOW!",MAX(Assumptions!I9,Assumptions!G9-INDIRECT(ADDRESS(ROW()-3,COLUMN()+Assumptions!F9))+INDIRECT(ADDRESS(ROW()-6,COLUMN()+Assumptions!F9))),"")}
A50: SKU006 | B50: Beginning Inventory | C50: =Assumptions!H10 -> 90 | D50: =C54 -> 84 | E50: =D54 -> 76 | F50: =E54 -> 67 | G50: =F54 -> 56 | H50: =G54 -> 43 | I50: =H54 -> 28 | J50: =I54 -> 11 | K50: =J54 -> 0 | ... N50: =M54 -> 0
B51: Gross Sales | C51: ='Demand Forecast'!C45 -> 6 | D51: ='Demand Forecast'!D45 -> 8 | E51: ='Demand Forecast'!E45 -> 9 | F51: ='Demand Forecast'!F45 -> 11 | G51: ='Demand Forecast'!G45 -> 13 | H51: ='Demand Forecast'!H45 -> 15 | I51: ='Demand Forecast'!I45 -> 17 | J51: ='Demand Forecast'!J45 -> 19 | ... N51: ='Demand Forecast'!N45 -> 27
B52: Net Position | C52: =C50-C51 -> 84 | D52: =D50-D51 -> 76 | E52: =E50-E51 -> 67 | F52: =F50-F51 -> 56 | G52: =G50-G51 -> 43 | H52: =H50-H51 -> 28 | I52: =I50-I51 -> 11 | J52: =J50-J51 -> -8 | ... N52: =N50-N51 -> -27
B53: Incoming Shipments ⚠️ | C53: 0 | D53: 0 | E53: 0 | F53: 0 | G53: 0 | H53: 0 | I53: 0 | J53: 0 | K53: 0 | L53: 0 | M53: 0 | N53: 0
B54: Ending Inventory | C54: =MAX(0,C52+C53) -> 84 | D54: =MAX(0,D52+D53) -> 76 | E54: =MAX(0,E52+E53) -> 67 | F54: =MAX(0,F52+F53) -> 56 | G54: =MAX(0,G52+G53) -> 43 | H54: =MAX(0,H52+H53) -> 28 | I54: =MAX(0,I52+I53) -> 11 | J54: =MAX(0,J52+J53) -> 0 | ... N54: =MAX(0,N52+N53) -> 0 | O54: =IF(N54<Assumptions!G10,"🚨 REORDER NOW",IF(N54<1.5*Assumptions!G10,"⚠️ ORDER SOON","✅ OK")) -> 🚨 REORDER NOW
B55: Months of Supply | C55: =IFERROR(C54/D51,"-") -> 10.5 | D55: =IFERROR(D54/E51,"-") -> 8.4444444 | E55: =IFERROR(E54/F51,"-") -> 6.0909091 | F55: =IFERROR(F54/G51,"-") -> 4.3076923 | G55: =IFERROR(G54/H51,"-") -> 2.8666667 | H55: =IFERROR(H54/I51,"-") -> 1.6470588 | I55: =IFERROR(I54/J51,"-") -> 0.57894737 | J55: =IFERROR(J54/K51,"-") -> 0 | ... M55: =IFERROR(M54/N51,"-") -> 0 | N55: -
B56: 🚨 Order Alert | C56: {=IF(COLUMN()+Assumptions!F10>14,"",IF(INDIRECT(ADDRESS(ROW()-2,COLUMN()+Assumptions!F10))<Assumptions!G10,"ORDER NOW!",""))} -> ORDER NOW! | D56: {=IF(COLUMN()+Assumptions!F10>14,"",IF(INDIRECT(ADDRESS(ROW()-2,COLUMN()+Assumptions!F10))<Assumptions!G10,"ORDER NOW!",""))} -> ORDER NOW! | E56: {=IF(COLUMN()+Assumptions!F10>14,"",IF(INDIRECT(ADDRESS(ROW()-2,COLUMN()+Assumptions!F10))<Assumptions!G10,"ORDER NOW!",""))} -> ORDER NOW! | F56: {=IF(COLUMN()+Assumptions!F10>14,"",IF(INDIRECT(ADDRESS(ROW()-2,COLUMN()+Assumptions!F10))<Assumptions!G10,"ORDER NOW!",""))} -> ORDER NOW! | G56: {=IF(COLUMN()+Assumptions!F10>14,"",IF(INDIRECT(ADDRESS(ROW()-2,COLUMN()+Assumptions!F10))<Assumptions!G10,"ORDER NOW!",""))} -> ORDER NOW! | H56: {=IF(COLUMN()+Assumptions!F10>14,"",IF(INDIRECT(ADDRESS(ROW()-2,COLUMN()+Assumptions!F10))<Assumptions!G10,"ORDER NOW!",""))} -> ORDER NOW! | I56: {=IF(COLUMN()+Assumptions!F10>14,"",IF(INDIRECT(ADDRESS(ROW()-2,COLUMN()+Assumptions!F10))<Assumptions!G10,"ORDER NOW!",""))} -> ORDER NOW! | J56: {=IF(COLUMN()+Assumptions!F10>14,"",IF(INDIRECT(ADDRESS(ROW()-2,COLUMN()+Assumptions!F10))<Assumptions!G10,"ORDER NOW!",""))} -> ORDER NOW! | K56: {=IF(COLUMN()+Assumptions!F10>14,"",IF(INDIRECT(ADDRESS(ROW()-2,COLUMN()+Assumptions!F10))<Assumptions!G10,"ORDER NOW!",""))} -> ORDER NOW! | L56: {=IF(COLUMN()+Assumptions!F10>14,"",IF(INDIRECT(ADDRESS(ROW()-2,COLUMN()+Assumptions!F10))<Assumptions!G10,"ORDER NOW!",""))} | M56: {=IF(COLUMN()+Assumptions!F10>14,"",IF(INDIRECT(ADDRESS(ROW()-2,COLUMN()+Assumptions!F10))<Assumptions!G10,"ORDER NOW!",""))} | N56: {=IF(COLUMN()+Assumptions!F10>14,"",IF(INDIRECT(ADDRESS(ROW()-2,COLUMN()+Assumptions!F10))<Assumptions!G10,"ORDER NOW!",""))}
B57: Order Qty Needed | C57: {=IF(C56="ORDER NOW!",MAX(Assumptions!I10,Assumptions!G10-INDIRECT(ADDRESS(ROW()-3,COLUMN()+Assumptions!F10))+INDIRECT(ADDRESS(ROW()-6,COLUMN()+Assumptions!F10))),"")} -> 50 | D57: {=IF(D56="ORDER NOW!",MAX(Assumptions!I10,Assumptions!G10-INDIRECT(ADDRESS(ROW()-3,COLUMN()+Assumptions!F10))+INDIRECT(ADDRESS(ROW()-6,COLUMN()+Assumptions!F10))),"")} -> 50 | E57: {=IF(E56="ORDER NOW!",MAX(Assumptions!I10,Assumptions!G10-INDIRECT(ADDRESS(ROW()-3,COLUMN()+Assumptions!F10))+INDIRECT(ADDRESS(ROW()-6,COLUMN()+Assumptions!F10))),"")} -> 57 | F57: {=IF(F56="ORDER NOW!",MAX(Assumptions!I10,Assumptions!G10-INDIRECT(ADDRESS(ROW()-3,COLUMN()+Assumptions!F10))+INDIRECT(ADDRESS(ROW()-6,COLUMN()+Assumptions!F10))),"")} -> 76 | G57: {=IF(G56="ORDER NOW!",MAX(Assumptions!I10,Assumptions!G10-INDIRECT(ADDRESS(ROW()-3,COLUMN()+Assumptions!F10))+INDIRECT(ADDRESS(ROW()-6,COLUMN()+Assumptions!F10))),"")} -> 89 | H57: {=IF(H56="ORDER NOW!",MAX(Assumptions!I10,Assumptions!G10-INDIRECT(ADDRESS(ROW()-3,COLUMN()+Assumptions!F10))+INDIRECT(ADDRESS(ROW()-6,COLUMN()+Assumptions!F10))),"")} -> 91 | I57: {=IF(I56="ORDER NOW!",MAX(Assumptions!I10,Assumptions!G10-INDIRECT(ADDRESS(ROW()-3,COLUMN()+Assumptions!F10))+INDIRECT(ADDRESS(ROW()-6,COLUMN()+Assumptions!F10))),"")} -> 93 | J57: {=IF(J56="ORDER NOW!",MAX(Assumptions!I10,Assumptions!G10-INDIRECT(ADDRESS(ROW()-3,COLUMN()+Assumptions!F10))+INDIRECT(ADDRESS(ROW()-6,COLUMN()+Assumptions!F10))),"")} -> 95 | K57: {=IF(K56="ORDER NOW!",MAX(Assumptions!I10,Assumptions!G10-INDIRECT(ADDRESS(ROW()-3,COLUMN()+Assumptions!F10))+INDIRECT(ADDRESS(ROW()-6,COLUMN()+Assumptions!F10))),"")} -> 97 | L57: {=IF(L56="ORDER NOW!",MAX(Assumptions!I10,Assumptions!G10-INDIRECT(ADDRESS(ROW()-3,COLUMN()+Assumptions!F10))+INDIRECT(ADDRESS(ROW()-6,COLUMN()+Assumptions!F10))),"")} | M57: {=IF(M56="ORDER NOW!",MAX(Assumptions!I10,Assumptions!G10-INDIRECT(ADDRESS(ROW()-3,COLUMN()+Assumptions!F10))+INDIRECT(ADDRESS(ROW()-6,COLUMN()+Assumptions!F10))),"")} | N57: {=IF(N56="ORDER NOW!",MAX(Assumptions!I10,Assumptions!G10-INDIRECT(ADDRESS(ROW()-3,COLUMN()+Assumptions!F10))+INDIRECT(ADDRESS(ROW()-6,COLUMN()+Assumptions!F10))),"")}
A59: SKU007 | B59: Beginning Inventory | C59: =Assumptions!H11 -> 800 | D59: =C63 -> 750 | E59: =D63 -> 695 | F59: =E63 -> 635 | G59: =F63 -> 570 | H59: =G63 -> 500 | I59: =H63 -> 425 | J59: =I63 -> 345 | K59: =J63 -> 260 | ... N59: =M63 -> 0
B60: Gross Sales | C60: ='Demand Forecast'!C46 -> 50 | D60: ='Demand Forecast'!D46 -> 55 | E60: ='Demand Forecast'!E46 -> 60 | F60: ='Demand Forecast'!F46 -> 65 | G60: ='Demand Forecast'!G46 -> 70 | H60: ='Demand Forecast'!H46 -> 75 | I60: ='Demand Forecast'!I46 -> 80 | J60: ='Demand Forecast'!J46 -> 85 | ... N60: ='Demand Forecast'!N46 -> 110
B61: Net Position | C61: =C59-C60 -> 750 | D61: =D59-D60 -> 695 | E61: =E59-E60 -> 635 | F61: =F59-F60 -> 570 | G61: =G59-G60 -> 500 | H61: =H59-H60 -> 425 | I61: =I59-I60 -> 345 | J61: =J59-J60 -> 260 | ... N61: =N59-N60 -> -110
B62: Incoming Shipments ⚠️ | C62: 0 | D62: 0 | E62: 0 | F62: 0 | G62: 0 | H62: 0 | I62: 0 | J62: 0 | K62: 0 | L62: 0 | M62: 0 | N62: 0
B63: Ending Inventory | C63: =MAX(0,C61+C62) -> 750 | D63: =MAX(0,D61+D62) -> 695 | E63: =MAX(0,E61+E62) -> 635 | F63: =MAX(0,F61+F62) -> 570 | G63: =MAX(0,G61+G62) -> 500 | H63: =MAX(0,H61+H62) -> 425 | I63: =MAX(0,I61+I62) -> 345 | J63: =MAX(0,J61+J62) -> 260 | ... N63: =MAX(0,N61+N62) -> 0 | O63: =IF(N63<Assumptions!G11,"🚨 REORDER NOW",IF(N63<1.5*Assumptions!G11,"⚠️ ORDER SOON","✅ OK")) -> 🚨 REORDER NOW
B64: Months of Supply | C64: =IFERROR(C63/D60,"-") -> 13.636364 | D64: =IFERROR(D63/E60,"-") -> 11.583333 | E64: =IFERROR(E63/F60,"-") -> 9.7692308 | F64: =IFERROR(F63/G60,"-") -> 8.1428571 | G64: =IFERROR(G63/H60,"-") -> 6.6666667 | H64: =IFERROR(H63/I60,"-") -> 5.3125 | I64: =IFERROR(I63/J60,"-") -> 4.0588235 | J64: =IFERROR(J63/K60,"-") -> 2.8888889 | ... M64: =IFERROR(M63/N60,"-") -> 0 | N64: -
B65: 🚨 Order Alert | C65: {=IF(COLUMN()+Assumptions!F11>14,"",IF(INDIRECT(ADDRESS(ROW()-2,COLUMN()+Assumptions!F11))<Assumptions!G11,"ORDER NOW!",""))} | D65: {=IF(COLUMN()+Assumptions!F11>14,"",IF(INDIRECT(ADDRESS(ROW()-2,COLUMN()+Assumptions!F11))<Assumptions!G11,"ORDER NOW!",""))} | E65: {=IF(COLUMN()+Assumptions!F11>14,"",IF(INDIRECT(ADDRESS(ROW()-2,COLUMN()+Assumptions!F11))<Assumptions!G11,"ORDER NOW!",""))} | F65: {=IF(COLUMN()+Assumptions!F11>14,"",IF(INDIRECT(ADDRESS(ROW()-2,COLUMN()+Assumptions!F11))<Assumptions!G11,"ORDER NOW!",""))} -> ORDER NOW! | G65: {=IF(COLUMN()+Assumptions!F11>14,"",IF(INDIRECT(ADDRESS(ROW()-2,COLUMN()+Assumptions!F11))<Assumptions!G11,"ORDER NOW!",""))} -> ORDER NOW! | H65: {=IF(COLUMN()+Assumptions!F11>14,"",IF(INDIRECT(ADDRESS(ROW()-2,COLUMN()+Assumptions!F11))<Assumptions!G11,"ORDER NOW!",""))} -> ORDER NOW! | I65: {=IF(COLUMN()+Assumptions!F11>14,"",IF(INDIRECT(ADDRESS(ROW()-2,COLUMN()+Assumptions!F11))<Assumptions!G11,"ORDER NOW!",""))} -> ORDER NOW! | J65: {=IF(COLUMN()+Assumptions!F11>14,"",IF(INDIRECT(ADDRESS(ROW()-2,COLUMN()+Assumptions!F11))<Assumptions!G11,"ORDER NOW!",""))} -> ORDER NOW! | K65: {=IF(COLUMN()+Assumptions!F11>14,"",IF(INDIRECT(ADDRESS(ROW()-2,COLUMN()+Assumptions!F11))<Assumptions!G11,"ORDER NOW!",""))} -> ORDER NOW! | L65: {=IF(COLUMN()+Assumptions!F11>14,"",IF(INDIRECT(ADDRESS(ROW()-2,COLUMN()+Assumptions!F11))<Assumptions!G11,"ORDER NOW!",""))} -> ORDER NOW! | M65: {=IF(COLUMN()+Assumptions!F11>14,"",IF(INDIRECT(ADDRESS(ROW()-2,COLUMN()+Assumptions!F11))<Assumptions!G11,"ORDER NOW!",""))} | N65: {=IF(COLUMN()+Assumptions!F11>14,"",IF(INDIRECT(ADDRESS(ROW()-2,COLUMN()+Assumptions!F11))<Assumptions!G11,"ORDER NOW!",""))}
B66: Order Qty Needed | C66: {=IF(C65="ORDER NOW!",MAX(Assumptions!I11,Assumptions!G11-INDIRECT(ADDRESS(ROW()-3,COLUMN()+Assumptions!F11))+INDIRECT(ADDRESS(ROW()-6,COLUMN()+Assumptions!F11))),"")} | D66: {=IF(D65="ORDER NOW!",MAX(Assumptions!I11,Assumptions!G11-INDIRECT(ADDRESS(ROW()-3,COLUMN()+Assumptions!F11))+INDIRECT(ADDRESS(ROW()-6,COLUMN()+Assumptions!F11))),"")} | E66: {=IF(E65="ORDER NOW!",MAX(Assumptions!I11,Assumptions!G11-INDIRECT(ADDRESS(ROW()-3,COLUMN()+Assumptions!F11))+INDIRECT(ADDRESS(ROW()-6,COLUMN()+Assumptions!F11))),"")} | F66: {=IF(F65="ORDER NOW!",MAX(Assumptions!I11,Assumptions!G11-INDIRECT(ADDRESS(ROW()-3,COLUMN()+Assumptions!F11))+INDIRECT(ADDRESS(ROW()-6,COLUMN()+Assumptions!F11))),"")} -> 200 | G66: {=IF(G65="ORDER NOW!",MAX(Assumptions!I11,Assumptions!G11-INDIRECT(ADDRESS(ROW()-3,COLUMN()+Assumptions!F11))+INDIRECT(ADDRESS(ROW()-6,COLUMN()+Assumptions!F11))),"")} -> 235 | H66: {=IF(H65="ORDER NOW!",MAX(Assumptions!I11,Assumptions!G11-INDIRECT(ADDRESS(ROW()-3,COLUMN()+Assumptions!F11))+INDIRECT(ADDRESS(ROW()-6,COLUMN()+Assumptions!F11))),"")} -> 325 | I66: {=IF(I65="ORDER NOW!",MAX(Assumptions!I11,Assumptions!G11-INDIRECT(ADDRESS(ROW()-3,COLUMN()+Assumptions!F11))+INDIRECT(ADDRESS(ROW()-6,COLUMN()+Assumptions!F11))),"")} -> 420 | J66: {=IF(J65="ORDER NOW!",MAX(Assumptions!I11,Assumptions!G11-INDIRECT(ADDRESS(ROW()-3,COLUMN()+Assumptions!F11))+INDIRECT(ADDRESS(ROW()-6,COLUMN()+Assumptions!F11))),"")} -> 520 | K66: {=IF(K65="ORDER NOW!",MAX(Assumptions!I11,Assumptions!G11-INDIRECT(ADDRESS(ROW()-3,COLUMN()+Assumptions!F11))+INDIRECT(ADDRESS(ROW()-6,COLUMN()+Assumptions!F11))),"")} -> 600 | L66: {=IF(L65="ORDER NOW!",MAX(Assumptions!I11,Assumptions!G11-INDIRECT(ADDRESS(ROW()-3,COLUMN()+Assumptions!F11))+INDIRECT(ADDRESS(ROW()-6,COLUMN()+Assumptions!F11))),"")} -> 610 | M66: {=IF(M65="ORDER NOW!",MAX(Assumptions!I11,Assumptions!G11-INDIRECT(ADDRESS(ROW()-3,COLUMN()+Assumptions!F11))+INDIRECT(ADDRESS(ROW()-6,COLUMN()+Assumptions!F11))),"")} | N66: {=IF(N65="ORDER NOW!",MAX(Assumptions!I11,Assumptions!G11-INDIRECT(ADDRESS(ROW()-3,COLUMN()+Assumptions!F11))+INDIRECT(ADDRESS(ROW()-6,COLUMN()+Assumptions!F11))),"")}
A68: SKU008 | B68: Beginning Inventory | C68: =Assumptions!H12 -> 600 | D68: =C72 -> 560 | E68: =D72 -> 515 | F68: =E72 -> 465 | G68: =F72 -> 410 | H68: =G72 -> 350 | I68: =H72 -> 285 | J68: =I72 -> 215 | K68: =J72 -> 140 | ... N68: =M72 -> 0
B69: Gross Sales | C69: ='Demand Forecast'!C47 -> 40 | D69: ='Demand Forecast'!D47 -> 45 | E69: ='Demand Forecast'!E47 -> 50 | F69: ='Demand Forecast'!F47 -> 55 | G69: ='Demand Forecast'!G47 -> 60 | H69: ='Demand Forecast'!H47 -> 65 | I69: ='Demand Forecast'!I47 -> 70 | J69: ='Demand Forecast'!J47 -> 75 | ... N69: ='Demand Forecast'!N47 -> 95
B70: Net Position | C70: =C68-C69 -> 560 | D70: =D68-D69 -> 515 | E70: =E68-E69 -> 465 | F70: =F68-F69 -> 410 | G70: =G68-G69 -> 350 | H70: =H68-H69 -> 285 | I70: =I68-I69 -> 215 | J70: =J68-J69 -> 140 | ... N70: =N68-N69 -> -95
B71: Incoming Shipments ⚠️ | C71: 0 | D71: 0 | E71: 0 | F71: 0 | G71: 0 | H71: 0 | I71: 0 | J71: 0 | K71: 0 | L71: 0 | M71: 0 | N71: 0
B72: Ending Inventory | C72: =MAX(0,C70+C71) -> 560 | D72: =MAX(0,D70+D71) -> 515 | E72: =MAX(0,E70+E71) -> 465 | F72: =MAX(0,F70+F71) -> 410 | G72: =MAX(0,G70+G71) -> 350 | H72: =MAX(0,H70+H71) -> 285 | I72: =MAX(0,I70+I71) -> 215 | J72: =MAX(0,J70+J71) -> 140 | ... N72: =MAX(0,N70+N71) -> 0 | O72: =IF(N72<Assumptions!G12,"🚨 REORDER NOW",IF(N72<1.5*Assumptions!G12,"⚠️ ORDER SOON","✅ OK")) -> 🚨 REORDER NOW
B73: Months of Supply | C73: =IFERROR(C72/D69,"-") -> 12.444444 | D73: =IFERROR(D72/E69,"-") -> 10.3 | E73: =IFERROR(E72/F69,"-") -> 8.4545455 | F73: =IFERROR(F72/G69,"-") -> 6.8333333 | G73: =IFERROR(G72/H69,"-") -> 5.3846154 | H73: =IFERROR(H72/I69,"-") -> 4.0714286 | I73: =IFERROR(I72/J69,"-") -> 2.8666667 | J73: =IFERROR(J72/K69,"-") -> 1.75 | ... M73: =IFERROR(M72/N69,"-") -> 0 | N73: -
B74: 🚨 Order Alert | C74: {=IF(COLUMN()+Assumptions!F12>14,"",IF(INDIRECT(ADDRESS(ROW()-2,COLUMN()+Assumptions!F12))<Assumptions!G12,"ORDER NOW!",""))} | D74: {=IF(COLUMN()+Assumptions!F12>14,"",IF(INDIRECT(ADDRESS(ROW()-2,COLUMN()+Assumptions!F12))<Assumptions!G12,"ORDER NOW!",""))} | E74: {=IF(COLUMN()+Assumptions!F12>14,"",IF(INDIRECT(ADDRESS(ROW()-2,COLUMN()+Assumptions!F12))<Assumptions!G12,"ORDER NOW!",""))} -> ORDER NOW! | F74: {=IF(COLUMN()+Assumptions!F12>14,"",IF(INDIRECT(ADDRESS(ROW()-2,COLUMN()+Assumptions!F12))<Assumptions!G12,"ORDER NOW!",""))} -> ORDER NOW! | G74: {=IF(COLUMN()+Assumptions!F12>14,"",IF(INDIRECT(ADDRESS(ROW()-2,COLUMN()+Assumptions!F12))<Assumptions!G12,"ORDER NOW!",""))} -> ORDER NOW! | H74: {=IF(COLUMN()+Assumptions!F12>14,"",IF(INDIRECT(ADDRESS(ROW()-2,COLUMN()+Assumptions!F12))<Assumptions!G12,"ORDER NOW!",""))} -> ORDER NOW! | I74: {=IF(COLUMN()+Assumptions!F12>14,"",IF(INDIRECT(ADDRESS(ROW()-2,COLUMN()+Assumptions!F12))<Assumptions!G12,"ORDER NOW!",""))} -> ORDER NOW! | J74: {=IF(COLUMN()+Assumptions!F12>14,"",IF(INDIRECT(ADDRESS(ROW()-2,COLUMN()+Assumptions!F12))<Assumptions!G12,"ORDER NOW!",""))} -> ORDER NOW! | K74: {=IF(COLUMN()+Assumptions!F12>14,"",IF(INDIRECT(ADDRESS(ROW()-2,COLUMN()+Assumptions!F12))<Assumptions!G12,"ORDER NOW!",""))} -> ORDER NOW! | L74: {=IF(COLUMN()+Assumptions!F12>14,"",IF(INDIRECT(ADDRESS(ROW()-2,COLUMN()+Assumptions!F12))<Assumptions!G12,"ORDER NOW!",""))} -> ORDER NOW! | M74: {=IF(COLUMN()+Assumptions!F12>14,"",IF(INDIRECT(ADDRESS(ROW()-2,COLUMN()+Assumptions!F12))<Assumptions!G12,"ORDER NOW!",""))} | N74: {=IF(COLUMN()+Assumptions!F12>14,"",IF(INDIRECT(ADDRESS(ROW()-2,COLUMN()+Assumptions!F12))<Assumptions!G12,"ORDER NOW!",""))}
B75: Order Qty Needed | C75: {=IF(C74="ORDER NOW!",MAX(Assumptions!I12,Assumptions!G12-INDIRECT(ADDRESS(ROW()-3,COLUMN()+Assumptions!F12))+INDIRECT(ADDRESS(ROW()-6,COLUMN()+Assumptions!F12))),"")} | D75: {=IF(D74="ORDER NOW!",MAX(Assumptions!I12,Assumptions!G12-INDIRECT(ADDRESS(ROW()-3,COLUMN()+Assumptions!F12))+INDIRECT(ADDRESS(ROW()-6,COLUMN()+Assumptions!F12))),"")} | E75: {=IF(E74="ORDER NOW!",MAX(Assumptions!I12,Assumptions!G12-INDIRECT(ADDRESS(ROW()-3,COLUMN()+Assumptions!F12))+INDIRECT(ADDRESS(ROW()-6,COLUMN()+Assumptions!F12))),"")} -> 200 | F75: {=IF(F74="ORDER NOW!",MAX(Assumptions!I12,Assumptions!G12-INDIRECT(ADDRESS(ROW()-3,COLUMN()+Assumptions!F12))+INDIRECT(ADDRESS(ROW()-6,COLUMN()+Assumptions!F12))),"")} -> 200 | G75: {=IF(G74="ORDER NOW!",MAX(Assumptions!I12,Assumptions!G12-INDIRECT(ADDRESS(ROW()-3,COLUMN()+Assumptions!F12))+INDIRECT(ADDRESS(ROW()-6,COLUMN()+Assumptions!F12))),"")} -> 255 | H75: {=IF(H74="ORDER NOW!",MAX(Assumptions!I12,Assumptions!G12-INDIRECT(ADDRESS(ROW()-3,COLUMN()+Assumptions!F12))+INDIRECT(ADDRESS(ROW()-6,COLUMN()+Assumptions!F12))),"")} -> 335 | I75: {=IF(I74="ORDER NOW!",MAX(Assumptions!I12,Assumptions!G12-INDIRECT(ADDRESS(ROW()-3,COLUMN()+Assumptions!F12))+INDIRECT(ADDRESS(ROW()-6,COLUMN()+Assumptions!F12))),"")} -> 420 | J75: {=IF(J74="ORDER NOW!",MAX(Assumptions!I12,Assumptions!G12-INDIRECT(ADDRESS(ROW()-3,COLUMN()+Assumptions!F12))+INDIRECT(ADDRESS(ROW()-6,COLUMN()+Assumptions!F12))),"")} -> 485 | K75: {=IF(K74="ORDER NOW!",MAX(Assumptions!I12,Assumptions!G12-INDIRECT(ADDRESS(ROW()-3,COLUMN()+Assumptions!F12))+INDIRECT(ADDRESS(ROW()-6,COLUMN()+Assumptions!F12))),"")} -> 490 | L75: {=IF(L74="ORDER NOW!",MAX(Assumptions!I12,Assumptions!G12-INDIRECT(ADDRESS(ROW()-3,COLUMN()+Assumptions!F12))+INDIRECT(ADDRESS(ROW()-6,COLUMN()+Assumptions!F12))),"")} -> 495 | M75: {=IF(M74="ORDER NOW!",MAX(Assumptions!I12,Assumptions!G12-INDIRECT(ADDRESS(ROW()-3,COLUMN()+Assumptions!F12))+INDIRECT(ADDRESS(ROW()-6,COLUMN()+Assumptions!F12))),"")} | N75: {=IF(N74="ORDER NOW!",MAX(Assumptions!I12,Assumptions!G12-INDIRECT(ADDRESS(ROW()-3,COLUMN()+Assumptions!F12))+INDIRECT(ADDRESS(ROW()-6,COLUMN()+Assumptions!F12))),"")}
A77: SKU009 | B77: Beginning Inventory | C77: =Assumptions!H13 -> 350 | D77: =C81 -> 320 | E77: =D81 -> 285 | F77: =E81 -> 245 | G77: =F81 -> 200 | H77: =G81 -> 150 | I77: =H81 -> 95 | J77: =I81 -> 35 | K77: =J81 -> 0 | ... N77: =M81 -> 0
B78: Gross Sales | C78: ='Demand Forecast'!C48 -> 30 | D78: ='Demand Forecast'!D48 -> 35 | E78: ='Demand Forecast'!E48 -> 40 | F78: ='Demand Forecast'!F48 -> 45 | G78: ='Demand Forecast'!G48 -> 50 | H78: ='Demand Forecast'!H48 -> 55 | I78: ='Demand Forecast'!I48 -> 60 | J78: ='Demand Forecast'!J48 -> 65 | ... N78: ='Demand Forecast'!N48 -> 85
B79: Net Position | C79: =C77-C78 -> 320 | D79: =D77-D78 -> 285 | E79: =E77-E78 -> 245 | F79: =F77-F78 -> 200 | G79: =G77-G78 -> 150 | H79: =H77-H78 -> 95 | I79: =I77-I78 -> 35 | J79: =J77-J78 -> -30 | ... N79: =N77-N78 -> -85
B80: Incoming Shipments ⚠️ | C80: 0 | D80: 0 | E80: 0 | F80: 0 | G80: 0 | H80: 0 | I80: 0 | J80: 0 | K80: 0 | L80: 0 | M80: 0 | N80: 0
B81: Ending Inventory | C81: =MAX(0,C79+C80) -> 320 | D81: =MAX(0,D79+D80) -> 285 | E81: =MAX(0,E79+E80) -> 245 | F81: =MAX(0,F79+F80) -> 200 | G81: =MAX(0,G79+G80) -> 150 | H81: =MAX(0,H79+H80) -> 95 | I81: =MAX(0,I79+I80) -> 35 | J81: =MAX(0,J79+J80) -> 0 | ... N81: =MAX(0,N79+N80) -> 0 | O81: =IF(N81<Assumptions!G13,"🚨 REORDER NOW",IF(N81<1.5*Assumptions!G13,"⚠️ ORDER SOON","✅ OK")) -> 🚨 REORDER NOW
B82: Months of Supply | C82: =IFERROR(C81/D78,"-") -> 9.1428571 | D82: =IFERROR(D81/E78,"-") -> 7.125 | E82: =IFERROR(E81/F78,"-") -> 5.4444444 | F82: =IFERROR(F81/G78,"-") -> 4 | G82: =IFERROR(G81/H78,"-") -> 2.7272727 | H82: =IFERROR(H81/I78,"-") -> 1.5833333 | I82: =IFERROR(I81/J78,"-") -> 0.53846154 | J82: =IFERROR(J81/K78,"-") -> 0 | ... M82: =IFERROR(M81/N78,"-") -> 0 | N82: -
B83: 🚨 Order Alert | C83: {=IF(COLUMN()+Assumptions!F13>14,"",IF(INDIRECT(ADDRESS(ROW()-2,COLUMN()+Assumptions!F13))<Assumptions!G13,"ORDER NOW!",""))} | D83: {=IF(COLUMN()+Assumptions!F13>14,"",IF(INDIRECT(ADDRESS(ROW()-2,COLUMN()+Assumptions!F13))<Assumptions!G13,"ORDER NOW!",""))} | E83: {=IF(COLUMN()+Assumptions!F13>14,"",IF(INDIRECT(ADDRESS(ROW()-2,COLUMN()+Assumptions!F13))<Assumptions!G13,"ORDER NOW!",""))} -> ORDER NOW! | F83: {=IF(COLUMN()+Assumptions!F13>14,"",IF(INDIRECT(ADDRESS(ROW()-2,COLUMN()+Assumptions!F13))<Assumptions!G13,"ORDER NOW!",""))} -> ORDER NOW! | G83: {=IF(COLUMN()+Assumptions!F13>14,"",IF(INDIRECT(ADDRESS(ROW()-2,COLUMN()+Assumptions!F13))<Assumptions!G13,"ORDER NOW!",""))} -> ORDER NOW! | H83: {=IF(COLUMN()+Assumptions!F13>14,"",IF(INDIRECT(ADDRESS(ROW()-2,COLUMN()+Assumptions!F13))<Assumptions!G13,"ORDER NOW!",""))} -> ORDER NOW! | I83: {=IF(COLUMN()+Assumptions!F13>14,"",IF(INDIRECT(ADDRESS(ROW()-2,COLUMN()+Assumptions!F13))<Assumptions!G13,"ORDER NOW!",""))} -> ORDER NOW! | J83: {=IF(COLUMN()+Assumptions!F13>14,"",IF(INDIRECT(ADDRESS(ROW()-2,COLUMN()+Assumptions!F13))<Assumptions!G13,"ORDER NOW!",""))} -> ORDER NOW! | K83: {=IF(COLUMN()+Assumptions!F13>14,"",IF(INDIRECT(ADDRESS(ROW()-2,COLUMN()+Assumptions!F13))<Assumptions!G13,"ORDER NOW!",""))} -> ORDER NOW! | L83: {=IF(COLUMN()+Assumptions!F13>14,"",IF(INDIRECT(ADDRESS(ROW()-2,COLUMN()+Assumptions!F13))<Assumptions!G13,"ORDER NOW!",""))} -> ORDER NOW! | M83: {=IF(COLUMN()+Assumptions!F13>14,"",IF(INDIRECT(ADDRESS(ROW()-2,COLUMN()+Assumptions!F13))<Assumptions!G13,"ORDER NOW!",""))} | N83: {=IF(COLUMN()+Assumptions!F13>14,"",IF(INDIRECT(ADDRESS(ROW()-2,COLUMN()+Assumptions!F13))<Assumptions!G13,"ORDER NOW!",""))}
B84: Order Qty Needed | C84: {=IF(C83="ORDER NOW!",MAX(Assumptions!I13,Assumptions!G13-INDIRECT(ADDRESS(ROW()-3,COLUMN()+Assumptions!F13))+INDIRECT(ADDRESS(ROW()-6,COLUMN()+Assumptions!F13))),"")} | D84: {=IF(D83="ORDER NOW!",MAX(Assumptions!I13,Assumptions!G13-INDIRECT(ADDRESS(ROW()-3,COLUMN()+Assumptions!F13))+INDIRECT(ADDRESS(ROW()-6,COLUMN()+Assumptions!F13))),"")} | E84: {=IF(E83="ORDER NOW!",MAX(Assumptions!I13,Assumptions!G13-INDIRECT(ADDRESS(ROW()-3,COLUMN()+Assumptions!F13))+INDIRECT(ADDRESS(ROW()-6,COLUMN()+Assumptions!F13))),"")} -> 100 | F84: {=IF(F83="ORDER NOW!",MAX(Assumptions!I13,Assumptions!G13-INDIRECT(ADDRESS(ROW()-3,COLUMN()+Assumptions!F13))+INDIRECT(ADDRESS(ROW()-6,COLUMN()+Assumptions!F13))),"")} -> 160 | G84: {=IF(G83="ORDER NOW!",MAX(Assumptions!I13,Assumptions!G13-INDIRECT(ADDRESS(ROW()-3,COLUMN()+Assumptions!F13))+INDIRECT(ADDRESS(ROW()-6,COLUMN()+Assumptions!F13))),"")} -> 225 | H84: {=IF(H83="ORDER NOW!",MAX(Assumptions!I13,Assumptions!G13-INDIRECT(ADDRESS(ROW()-3,COLUMN()+Assumptions!F13))+INDIRECT(ADDRESS(ROW()-6,COLUMN()+Assumptions!F13))),"")} -> 265 | I84: {=IF(I83="ORDER NOW!",MAX(Assumptions!I13,Assumptions!G13-INDIRECT(ADDRESS(ROW()-3,COLUMN()+Assumptions!F13))+INDIRECT(ADDRESS(ROW()-6,COLUMN()+Assumptions!F13))),"")} -> 270 | J84: {=IF(J83="ORDER NOW!",MAX(Assumptions!I13,Assumptions!G13-INDIRECT(ADDRESS(ROW()-3,COLUMN()+Assumptions!F13))+INDIRECT(ADDRESS(ROW()-6,COLUMN()+Assumptions!F13))),"")} -> 275 | K84: {=IF(K83="ORDER NOW!",MAX(Assumptions!I13,Assumptions!G13-INDIRECT(ADDRESS(ROW()-3,COLUMN()+Assumptions!F13))+INDIRECT(ADDRESS(ROW()-6,COLUMN()+Assumptions!F13))),"")} -> 280 | L84: {=IF(L83="ORDER NOW!",MAX(Assumptions!I13,Assumptions!G13-INDIRECT(ADDRESS(ROW()-3,COLUMN()+Assumptions!F13))+INDIRECT(ADDRESS(ROW()-6,COLUMN()+Assumptions!F13))),"")} -> 285 | M84: {=IF(M83="ORDER NOW!",MAX(Assumptions!I13,Assumptions!G13-INDIRECT(ADDRESS(ROW()-3,COLUMN()+Assumptions!F13))+INDIRECT(ADDRESS(ROW()-6,COLUMN()+Assumptions!F13))),"")} | N84: {=IF(N83="ORDER NOW!",MAX(Assumptions!I13,Assumptions!G13-INDIRECT(ADDRESS(ROW()-3,COLUMN()+Assumptions!F13))+INDIRECT(ADDRESS(ROW()-6,COLUMN()+Assumptions!F13))),"")}
A86: SKU010 | B86: Beginning Inventory | C86: =Assumptions!H14 -> 300 | D86: =C90 -> 275 | E86: =D90 -> 247 | F86: =E90 -> 217 | G86: =F90 -> 184 | H86: =G90 -> 148 | I86: =H90 -> 108 | J86: =I90 -> 64 | K86: =J90 -> 16 | ... N86: =M90 -> 0
B87: Gross Sales | C87: ='Demand Forecast'!C49 -> 25 | D87: ='Demand Forecast'!D49 -> 28 | E87: ='Demand Forecast'!E49 -> 30 | F87: ='Demand Forecast'!F49 -> 33 | G87: ='Demand Forecast'!G49 -> 36 | H87: ='Demand Forecast'!H49 -> 40 | I87: ='Demand Forecast'!I49 -> 44 | J87: ='Demand Forecast'!J49 -> 48 | ... N87: ='Demand Forecast'!N49 -> 65
B88: Net Position | C88: =C86-C87 -> 275 | D88: =D86-D87 -> 247 | E88: =E86-E87 -> 217 | F88: =F86-F87 -> 184 | G88: =G86-G87 -> 148 | H88: =H86-H87 -> 108 | I88: =I86-I87 -> 64 | J88: =J86-J87 -> 16 | ... N88: =N86-N87 -> -65
B89: Incoming Shipments ⚠️ | C89: 0 | D89: 0 | E89: 0 | F89: 0 | G89: 0 | H89: 0 | I89: 0 | J89: 0 | K89: 0 | L89: 0 | M89: 0 | N89: 0
B90: Ending Inventory | C90: =MAX(0,C88+C89) -> 275 | D90: =MAX(0,D88+D89) -> 247 | E90: =MAX(0,E88+E89) -> 217 | F90: =MAX(0,F88+F89) -> 184 | G90: =MAX(0,G88+G89) -> 148 | H90: =MAX(0,H88+H89) -> 108 | I90: =MAX(0,I88+I89) -> 64 | J90: =MAX(0,J88+J89) -> 16 | ... N90: =MAX(0,N88+N89) -> 0 | O90: =IF(N90<Assumptions!G14,"🚨 REORDER NOW",IF(N90<1.5*Assumptions!G14,"⚠️ ORDER SOON","✅ OK")) -> 🚨 REORDER NOW
B91: Months of Supply | C91: =IFERROR(C90/D87,"-") -> 9.8214286 | D91: =IFERROR(D90/E87,"-") -> 8.2333333 | E91: =IFERROR(E90/F87,"-") -> 6.5757576 | F91: =IFERROR(F90/G87,"-") -> 5.1111111 | G91: =IFERROR(G90/H87,"-") -> 3.7 | H91: =IFERROR(H90/I87,"-") -> 2.4545455 | I91: =IFERROR(I90/J87,"-") -> 1.3333333 | J91: =IFERROR(J90/K87,"-") -> 0.30769231 | ... M91: =IFERROR(M90/N87,"-") -> 0 | N91: -
B92: 🚨 Order Alert | C92: {=IF(COLUMN()+Assumptions!F14>14,"",IF(INDIRECT(ADDRESS(ROW()-2,COLUMN()+Assumptions!F14))<Assumptions!G14,"ORDER NOW!",""))} | D92: {=IF(COLUMN()+Assumptions!F14>14,"",IF(INDIRECT(ADDRESS(ROW()-2,COLUMN()+Assumptions!F14))<Assumptions!G14,"ORDER NOW!",""))} | E92: {=IF(COLUMN()+Assumptions!F14>14,"",IF(INDIRECT(ADDRESS(ROW()-2,COLUMN()+Assumptions!F14))<Assumptions!G14,"ORDER NOW!",""))} -> ORDER NOW! | F92: {=IF(COLUMN()+Assumptions!F14>14,"",IF(INDIRECT(ADDRESS(ROW()-2,COLUMN()+Assumptions!F14))<Assumptions!G14,"ORDER NOW!",""))} -> ORDER NOW! | G92: {=IF(COLUMN()+Assumptions!F14>14,"",IF(INDIRECT(ADDRESS(ROW()-2,COLUMN()+Assumptions!F14))<Assumptions!G14,"ORDER NOW!",""))} -> ORDER NOW! | H92: {=IF(COLUMN()+Assumptions!F14>14,"",IF(INDIRECT(ADDRESS(ROW()-2,COLUMN()+Assumptions!F14))<Assumptions!G14,"ORDER NOW!",""))} -> ORDER NOW! | I92: {=IF(COLUMN()+Assumptions!F14>14,"",IF(INDIRECT(ADDRESS(ROW()-2,COLUMN()+Assumptions!F14))<Assumptions!G14,"ORDER NOW!",""))} -> ORDER NOW! | J92: {=IF(COLUMN()+Assumptions!F14>14,"",IF(INDIRECT(ADDRESS(ROW()-2,COLUMN()+Assumptions!F14))<Assumptions!G14,"ORDER NOW!",""))} -> ORDER NOW! | K92: {=IF(COLUMN()+Assumptions!F14>14,"",IF(INDIRECT(ADDRESS(ROW()-2,COLUMN()+Assumptions!F14))<Assumptions!G14,"ORDER NOW!",""))} -> ORDER NOW! | L92: {=IF(COLUMN()+Assumptions!F14>14,"",IF(INDIRECT(ADDRESS(ROW()-2,COLUMN()+Assumptions!F14))<Assumptions!G14,"ORDER NOW!",""))} -> ORDER NOW! | M92: {=IF(COLUMN()+Assumptions!F14>14,"",IF(INDIRECT(ADDRESS(ROW()-2,COLUMN()+Assumptions!F14))<Assumptions!G14,"ORDER NOW!",""))} | N92: {=IF(COLUMN()+Assumptions!F14>14,"",IF(INDIRECT(ADDRESS(ROW()-2,COLUMN()+Assumptions!F14))<Assumptions!G14,"ORDER NOW!",""))}
B93: Order Qty Needed | C93: {=IF(C92="ORDER NOW!",MAX(Assumptions!I14,Assumptions!G14-INDIRECT(ADDRESS(ROW()-3,COLUMN()+Assumptions!F14))+INDIRECT(ADDRESS(ROW()-6,COLUMN()+Assumptions!F14))),"")} | D93: {=IF(D92="ORDER NOW!",MAX(Assumptions!I14,Assumptions!G14-INDIRECT(ADDRESS(ROW()-3,COLUMN()+Assumptions!F14))+INDIRECT(ADDRESS(ROW()-6,COLUMN()+Assumptions!F14))),"")} | E93: {=IF(E92="ORDER NOW!",MAX(Assumptions!I14,Assumptions!G14-INDIRECT(ADDRESS(ROW()-3,COLUMN()+Assumptions!F14))+INDIRECT(ADDRESS(ROW()-6,COLUMN()+Assumptions!F14))),"")} -> 75 | F93: {=IF(F92="ORDER NOW!",MAX(Assumptions!I14,Assumptions!G14-INDIRECT(ADDRESS(ROW()-3,COLUMN()+Assumptions!F14))+INDIRECT(ADDRESS(ROW()-6,COLUMN()+Assumptions!F14))),"")} -> 82 | G93: {=IF(G92="ORDER NOW!",MAX(Assumptions!I14,Assumptions!G14-INDIRECT(ADDRESS(ROW()-3,COLUMN()+Assumptions!F14))+INDIRECT(ADDRESS(ROW()-6,COLUMN()+Assumptions!F14))),"")} -> 130 | H93: {=IF(H92="ORDER NOW!",MAX(Assumptions!I14,Assumptions!G14-INDIRECT(ADDRESS(ROW()-3,COLUMN()+Assumptions!F14))+INDIRECT(ADDRESS(ROW()-6,COLUMN()+Assumptions!F14))),"")} -> 182 | I93: {=IF(I92="ORDER NOW!",MAX(Assumptions!I14,Assumptions!G14-INDIRECT(ADDRESS(ROW()-3,COLUMN()+Assumptions!F14))+INDIRECT(ADDRESS(ROW()-6,COLUMN()+Assumptions!F14))),"")} -> 202 | J93: {=IF(J92="ORDER NOW!",MAX(Assumptions!I14,Assumptions!G14-INDIRECT(ADDRESS(ROW()-3,COLUMN()+Assumptions!F14))+INDIRECT(ADDRESS(ROW()-6,COLUMN()+Assumptions!F14))),"")} -> 206 | K93: {=IF(K92="ORDER NOW!",MAX(Assumptions!I14,Assumptions!G14-INDIRECT(ADDRESS(ROW()-3,COLUMN()+Assumptions!F14))+INDIRECT(ADDRESS(ROW()-6,COLUMN()+Assumptions!F14))),"")} -> 210 | L93: {=IF(L92="ORDER NOW!",MAX(Assumptions!I14,Assumptions!G14-INDIRECT(ADDRESS(ROW()-3,COLUMN()+Assumptions!F14))+INDIRECT(ADDRESS(ROW()-6,COLUMN()+Assumptions!F14))),"")} -> 215 | M93: {=IF(M92="ORDER NOW!",MAX(Assumptions!I14,Assumptions!G14-INDIRECT(ADDRESS(ROW()-3,COLUMN()+Assumptions!F14))+INDIRECT(ADDRESS(ROW()-6,COLUMN()+Assumptions!F14))),"")} | N93: {=IF(N92="ORDER NOW!",MAX(Assumptions!I14,Assumptions!G14-INDIRECT(ADDRESS(ROW()-3,COLUMN()+Assumptions!F14))+INDIRECT(ADDRESS(ROW()-6,COLUMN()+Assumptions!F14))),"")}

Sheet Financial Summary
A1: FINANCIAL SUMMARY
A2: Monthly revenue, costs, margins, and cash flow
A4: REVENUE
A5: Line Item | B5: Description | C5: January | D5: February | E5: March | F5: April | G5: May | H5: June | I5: July | J5: August | K5: September | L5: October | M5: November | N5: December
A6: DTC Revenue | B6: (units × DTC price) | C6: =('Demand Forecast'!C6*Assumptions!D5)+('Demand Forecast'!C7*Assumptions!D6)+('Demand Forecast'!C8*Assumptions!D7)+('Demand Forecast'!C9*Assumptions!D8)+('Demand Forecast'!C10*Assumptions!D9)+('Demand Forecast'!C11*Assumptions!D10)+('Demand Forecast'!C12*Assumptions!D11)+('Demand Forecast'!C13*Assumptions!D12)+('Demand Forecast'!C14*Assumptions!D13)+('Demand Forecast'!C15*Assumptions!D14) -> 22609.97 | D6: =('Demand Forecast'!D6*Assumptions!D5)+('Demand Forecast'!D7*Assumptions!D6)+('Demand Forecast'!D8*Assumptions!D7)+('Demand Forecast'!D9*Assumptions!D8)+('Demand Forecast'!D10*Assumptions!D9)+('Demand Forecast'!D11*Assumptions!D10)+('Demand Forecast'!D12*Assumptions!D11)+('Demand Forecast'!D13*Assumptions!D12)+('Demand Forecast'!D14*Assumptions!D13)+('Demand Forecast'!D15*Assumptions!D14) -> 27421.66 | E6: =('Demand Forecast'!E6*Assumptions!D5)+('Demand Forecast'!E7*Assumptions!D6)+('Demand Forecast'!E8*Assumptions!D7)+('Demand Forecast'!E9*Assumptions!D8)+('Demand Forecast'!E10*Assumptions!D9)+('Demand Forecast'!E11*Assumptions!D10)+('Demand Forecast'!E12*Assumptions!D11)+('Demand Forecast'!E13*Assumptions!D12)+('Demand Forecast'!E14*Assumptions!D13)+('Demand Forecast'!E15*Assumptions!D14) -> 30807.4 | F6: =('Demand Forecast'!F6*Assumptions!D5)+('Demand Forecast'!F7*Assumptions!D6)+('Demand Forecast'!F8*Assumptions!D7)+('Demand Forecast'!F9*Assumptions!D8)+('Demand Forecast'!F10*Assumptions!D9)+('Demand Forecast'!F11*Assumptions!D10)+('Demand Forecast'!F12*Assumptions!D11)+('Demand Forecast'!F13*Assumptions!D12)+('Demand Forecast'!F14*Assumptions!D13)+('Demand Forecast'!F15*Assumptions!D14) -> 34931.11 | G6: =('Demand Forecast'!G6*Assumptions!D5)+('Demand Forecast'!G7*Assumptions!D6)+('Demand Forecast'!G8*Assumptions!D7)+('Demand Forecast'!G9*Assumptions!D8)+('Demand Forecast'!G10*Assumptions!D9)+('Demand Forecast'!G11*Assumptions!D10)+('Demand Forecast'!G12*Assumptions!D11)+('Demand Forecast'!G13*Assumptions!D12)+('Demand Forecast'!G14*Assumptions!D13)+('Demand Forecast'!G15*Assumptions!D14) -> 39742.8 | H6: =('Demand Forecast'!H6*Assumptions!D5)+('Demand Forecast'!H7*Assumptions!D6)+('Demand Forecast'!H8*Assumptions!D7)+('Demand Forecast'!H9*Assumptions!D8)+('Demand Forecast'!H10*Assumptions!D9)+('Demand Forecast'!H11*Assumptions!D10)+('Demand Forecast'!H12*Assumptions!D11)+('Demand Forecast'!H13*Assumptions!D12)+('Demand Forecast'!H14*Assumptions!D13)+('Demand Forecast'!H15*Assumptions!D14) -> 44604.48 | I6: =('Demand Forecast'!I6*Assumptions!D5)+('Demand Forecast'!I7*Assumptions!D6)+('Demand Forecast'!I8*Assumptions!D7)+('Demand Forecast'!I9*Assumptions!D8)+('Demand Forecast'!I10*Assumptions!D9)+('Demand Forecast'!I11*Assumptions!D10)+('Demand Forecast'!I12*Assumptions!D11)+('Demand Forecast'!I13*Assumptions!D12)+('Demand Forecast'!I14*Assumptions!D13)+('Demand Forecast'!I15*Assumptions!D14) -> 49122.17 | J6: =('Demand Forecast'!J6*Assumptions!D5)+('Demand Forecast'!J7*Assumptions!D6)+('Demand Forecast'!J8*Assumptions!D7)+('Demand Forecast'!J9*Assumptions!D8)+('Demand Forecast'!J10*Assumptions!D9)+('Demand Forecast'!J11*Assumptions!D10)+('Demand Forecast'!J12*Assumptions!D11)+('Demand Forecast'!J13*Assumptions!D12)+('Demand Forecast'!J14*Assumptions!D13)+('Demand Forecast'!J15*Assumptions!D14) -> 53639.86 | K6: =('Demand Forecast'!K6*Assumptions!D5)+('Demand Forecast'!K7*Assumptions!D6)+('Demand Forecast'!K8*Assumptions!D7)+('Demand Forecast'!K9*Assumptions!D8)+('Demand Forecast'!K10*Assumptions!D9)+('Demand Forecast'!K11*Assumptions!D10)+('Demand Forecast'!K12*Assumptions!D11)+('Demand Forecast'!K13*Assumptions!D12)+('Demand Forecast'!K14*Assumptions!D13)+('Demand Forecast'!K15*Assumptions!D14) -> 58501.54 | L6: =('Demand Forecast'!L6*Assumptions!D5)+('Demand Forecast'!L7*Assumptions!D6)+('Demand Forecast'!L8*Assumptions!D7)+('Demand Forecast'!L9*Assumptions!D8)+('Demand Forecast'!L10*Assumptions!D9)+('Demand Forecast'!L11*Assumptions!D10)+('Demand Forecast'!L12*Assumptions!D11)+('Demand Forecast'!L13*Assumptions!D12)+('Demand Forecast'!L14*Assumptions!D13)+('Demand Forecast'!L15*Assumptions!D14) -> 63363.22 | M6: =('Demand Forecast'!M6*Assumptions!D5)+('Demand Forecast'!M7*Assumptions!D6)+('Demand Forecast'!M8*Assumptions!D7)+('Demand Forecast'!M9*Assumptions!D8)+('Demand Forecast'!M10*Assumptions!D9)+('Demand Forecast'!M11*Assumptions!D10)+('Demand Forecast'!M12*Assumptions!D11)+('Demand Forecast'!M13*Assumptions!D12)+('Demand Forecast'!M14*Assumptions!D13)+('Demand Forecast'!M15*Assumptions!D14) -> 67880.91 | N6: =('Demand Forecast'!N6*Assumptions!D5)+('Demand Forecast'!N7*Assumptions!D6)+('Demand Forecast'!N8*Assumptions!D7)+('Demand Forecast'!N9*Assumptions!D8)+('Demand Forecast'!N10*Assumptions!D9)+('Demand Forecast'!N11*Assumptions!D10)+('Demand Forecast'!N12*Assumptions!D11)+('Demand Forecast'!N13*Assumptions!D12)+('Demand Forecast'!N14*Assumptions!D13)+('Demand Forecast'!N15*Assumptions!D14) -> 74557.48
A7: Wholesale Revenue | B7: (units × wholesale price) | C7: =('Demand Forecast'!C18*Assumptions!E5)+('Demand Forecast'!C19*Assumptions!E5)+('Demand Forecast'!C20*Assumptions!E6)+('Demand Forecast'!C21*Assumptions!E6)+('Demand Forecast'!C22*Assumptions!E7)+('Demand Forecast'!C23*Assumptions!E7)+('Demand Forecast'!C24*Assumptions!E8)+('Demand Forecast'!C25*Assumptions!E8)+('Demand Forecast'!C26*Assumptions!E9)+('Demand Forecast'!C27*Assumptions!E9)+('Demand Forecast'!C28*Assumptions!E10)+('Demand Forecast'!C29*Assumptions!E10)+('Demand Forecast'!C30*Assumptions!E11)+('Demand Forecast'!C31*Assumptions!E11)+('Demand Forecast'!C32*Assumptions!E12)+('Demand Forecast'!C33*Assumptions!E12)+('Demand Forecast'!C34*Assumptions!E13)+('Demand Forecast'!C35*Assumptions!E13)+('Demand Forecast'!C36*Assumptions!E14)+('Demand Forecast'!C37*Assumptions!E14) -> 0 | D7: =('Demand Forecast'!D18*Assumptions!E5)+('Demand Forecast'!D19*Assumptions!E5)+('Demand Forecast'!D20*Assumptions!E6)+('Demand Forecast'!D21*Assumptions!E6)+('Demand Forecast'!D22*Assumptions!E7)+('Demand Forecast'!D23*Assumptions!E7)+('Demand Forecast'!D24*Assumptions!E8)+('Demand Forecast'!D25*Assumptions!E8)+('Demand Forecast'!D26*Assumptions!E9)+('Demand Forecast'!D27*Assumptions!E9)+('Demand Forecast'!D28*Assumptions!E10)+('Demand Forecast'!D29*Assumptions!E10)+('Demand Forecast'!D30*Assumptions!E11)+('Demand Forecast'!D31*Assumptions!E11)+('Demand Forecast'!D32*Assumptions!E12)+('Demand Forecast'!D33*Assumptions!E12)+('Demand Forecast'!D34*Assumptions!E13)+('Demand Forecast'!D35*Assumptions!E13)+('Demand Forecast'!D36*Assumptions!E14)+('Demand Forecast'!D37*Assumptions!E14) -> 85425 | E7: =('Demand Forecast'!E18*Assumptions!E5)+('Demand Forecast'!E19*Assumptions!E5)+('Demand Forecast'!E20*Assumptions!E6)+('Demand Forecast'!E21*Assumptions!E6)+('Demand Forecast'!E22*Assumptions!E7)+('Demand Forecast'!E23*Assumptions!E7)+('Demand Forecast'!E24*Assumptions!E8)+('Demand Forecast'!E25*Assumptions!E8)+('Demand Forecast'!E26*Assumptions!E9)+('Demand Forecast'!E27*Assumptions!E9)+('Demand Forecast'!E28*Assumptions!E10)+('Demand Forecast'!E29*Assumptions!E10)+('Demand Forecast'!E30*Assumptions!E11)+('Demand Forecast'!E31*Assumptions!E11)+('Demand Forecast'!E32*Assumptions!E12)+('Demand Forecast'!E33*Assumptions!E12)+('Demand Forecast'!E34*Assumptions!E13)+('Demand Forecast'!E35*Assumptions!E13)+('Demand Forecast'!E36*Assumptions!E14)+('Demand Forecast'!E37*Assumptions!E14) -> 115700 | F7: =('Demand Forecast'!F18*Assumptions!E5)+('Demand Forecast'!F19*Assumptions!E5)+('Demand Forecast'!F20*Assumptions!E6)+('Demand Forecast'!F21*Assumptions!E6)+('Demand Forecast'!F22*Assumptions!E7)+('Demand Forecast'!F23*Assumptions!E7)+('Demand Forecast'!F24*Assumptions!E8)+('Demand Forecast'!F25*Assumptions!E8)+('Demand Forecast'!F26*Assumptions!E9)+('Demand Forecast'!F27*Assumptions!E9)+('Demand Forecast'!F28*Assumptions!E10)+('Demand Forecast'!F29*Assumptions!E10)+('Demand Forecast'!F30*Assumptions!E11)+('Demand Forecast'!F31*Assumptions!E11)+('Demand Forecast'!F32*Assumptions!E12)+('Demand Forecast'!F33*Assumptions!E12)+('Demand Forecast'!F34*Assumptions!E13)+('Demand Forecast'!F35*Assumptions!E13)+('Demand Forecast'!F36*Assumptions!E14)+('Demand Forecast'!F37*Assumptions!E14) -> 0 | G7: =('Demand Forecast'!G18*Assumptions!E5)+('Demand Forecast'!G19*Assumptions!E5)+('Demand Forecast'!G20*Assumptions!E6)+('Demand Forecast'!G21*Assumptions!E6)+('Demand Forecast'!G22*Assumptions!E7)+('Demand Forecast'!G23*Assumptions!E7)+('Demand Forecast'!G24*Assumptions!E8)+('Demand Forecast'!G25*Assumptions!E8)+('Demand Forecast'!G26*Assumptions!E9)+('Demand Forecast'!G27*Assumptions!E9)+('Demand Forecast'!G28*Assumptions!E10)+('Demand Forecast'!G29*Assumptions!E10)+('Demand Forecast'!G30*Assumptions!E11)+('Demand Forecast'!G31*Assumptions!E11)+('Demand Forecast'!G32*Assumptions!E12)+('Demand Forecast'!G33*Assumptions!E12)+('Demand Forecast'!G34*Assumptions!E13)+('Demand Forecast'!G35*Assumptions!E13)+('Demand Forecast'!G36*Assumptions!E14)+('Demand Forecast'!G37*Assumptions!E14) -> 0 | H7: =('Demand Forecast'!H18*Assumptions!E5)+('Demand Forecast'!H19*Assumptions!E5)+('Demand Forecast'!H20*Assumptions!E6)+('Demand Forecast'!H21*Assumptions!E6)+('Demand Forecast'!H22*Assumptions!E7)+('Demand Forecast'!H23*Assumptions!E7)+('Demand Forecast'!H24*Assumptions!E8)+('Demand Forecast'!H25*Assumptions!E8)+('Demand Forecast'!H26*Assumptions!E9)+('Demand Forecast'!H27*Assumptions!E9)+('Demand Forecast'!H28*Assumptions!E10)+('Demand Forecast'!H29*Assumptions!E10)+('Demand Forecast'!H30*Assumptions!E11)+('Demand Forecast'!H31*Assumptions!E11)+('Demand Forecast'!H32*Assumptions!E12)+('Demand Forecast'!H33*Assumptions!E12)+('Demand Forecast'!H34*Assumptions!E13)+('Demand Forecast'!H35*Assumptions!E13)+('Demand Forecast'!H36*Assumptions!E14)+('Demand Forecast'!H37*Assumptions!E14) -> 122650 | I7: =('Demand Forecast'!I18*Assumptions!E5)+('Demand Forecast'!I19*Assumptions!E5)+('Demand Forecast'!I20*Assumptions!E6)+('Demand Forecast'!I21*Assumptions!E6)+('Demand Forecast'!I22*Assumptions!E7)+('Demand Forecast'!I23*Assumptions!E7)+('Demand Forecast'!I24*Assumptions!E8)+('Demand Forecast'!I25*Assumptions!E8)+('Demand Forecast'!I26*Assumptions!E9)+('Demand Forecast'!I27*Assumptions!E9)+('Demand Forecast'!I28*Assumptions!E10)+('Demand Forecast'!I29*Assumptions!E10)+('Demand Forecast'!I30*Assumptions!E11)+('Demand Forecast'!I31*Assumptions!E11)+('Demand Forecast'!I32*Assumptions!E12)+('Demand Forecast'!I33*Assumptions!E12)+('Demand Forecast'!I34*Assumptions!E13)+('Demand Forecast'!I35*Assumptions!E13)+('Demand Forecast'!I36*Assumptions!E14)+('Demand Forecast'!I37*Assumptions!E14) -> 170850 | J7: =('Demand Forecast'!J18*Assumptions!E5)+('Demand Forecast'!J19*Assumptions!E5)+('Demand Forecast'!J20*Assumptions!E6)+('Demand Forecast'!J21*Assumptions!E6)+('Demand Forecast'!J22*Assumptions!E7)+('Demand Forecast'!J23*Assumptions!E7)+('Demand Forecast'!J24*Assumptions!E8)+('Demand Forecast'!J25*Assumptions!E8)+('Demand Forecast'!J26*Assumptions!E9)+('Demand Forecast'!J27*Assumptions!E9)+('Demand Forecast'!J28*Assumptions!E10)+('Demand Forecast'!J29*Assumptions!E10)+('Demand Forecast'!J30*Assumptions!E11)+('Demand Forecast'!J31*Assumptions!E11)+('Demand Forecast'!J32*Assumptions!E12)+('Demand Forecast'!J33*Assumptions!E12)+('Demand Forecast'!J34*Assumptions!E13)+('Demand Forecast'!J35*Assumptions!E13)+('Demand Forecast'!J36*Assumptions!E14)+('Demand Forecast'!J37*Assumptions!E14) -> 0 | K7: =('Demand Forecast'!K18*Assumptions!E5)+('Demand Forecast'!K19*Assumptions!E5)+('Demand Forecast'!K20*Assumptions!E6)+('Demand Forecast'!K21*Assumptions!E6)+('Demand Forecast'!K22*Assumptions!E7)+('Demand Forecast'!K23*Assumptions!E7)+('Demand Forecast'!K24*Assumptions!E8)+('Demand Forecast'!K25*Assumptions!E8)+('Demand Forecast'!K26*Assumptions!E9)+('Demand Forecast'!K27*Assumptions!E9)+('Demand Forecast'!K28*Assumptions!E10)+('Demand Forecast'!K29*Assumptions!E10)+('Demand Forecast'!K30*Assumptions!E11)+('Demand Forecast'!K31*Assumptions!E11)+('Demand Forecast'!K32*Assumptions!E12)+('Demand Forecast'!K33*Assumptions!E12)+('Demand Forecast'!K34*Assumptions!E13)+('Demand Forecast'!K35*Assumptions!E13)+('Demand Forecast'!K36*Assumptions!E14)+('Demand Forecast'!K37*Assumptions!E14) -> 0 | L7: =('Demand Forecast'!L18*Assumptions!E5)+('Demand Forecast'!L19*Assumptions!E5)+('Demand Forecast'!L20*Assumptions!E6)+('Demand Forecast'!L21*Assumptions!E6)+('Demand Forecast'!L22*Assumptions!E7)+('Demand Forecast'!L23*Assumptions!E7)+('Demand Forecast'!L24*Assumptions!E8)+('Demand Forecast'!L25*Assumptions!E8)+('Demand Forecast'!L26*Assumptions!E9)+('Demand Forecast'!L27*Assumptions!E9)+('Demand Forecast'!L28*Assumptions!E10)+('Demand Forecast'!L29*Assumptions!E10)+('Demand Forecast'!L30*Assumptions!E11)+('Demand Forecast'!L31*Assumptions!E11)+('Demand Forecast'!L32*Assumptions!E12)+('Demand Forecast'!L33*Assumptions!E12)+('Demand Forecast'!L34*Assumptions!E13)+('Demand Forecast'!L35*Assumptions!E13)+('Demand Forecast'!L36*Assumptions!E14)+('Demand Forecast'!L37*Assumptions!E14) -> 157100 | M7: =('Demand Forecast'!M18*Assumptions!E5)+('Demand Forecast'!M19*Assumptions!E5)+('Demand Forecast'!M20*Assumptions!E6)+('Demand Forecast'!M21*Assumptions!E6)+('Demand Forecast'!M22*Assumptions!E7)+('Demand Forecast'!M23*Assumptions!E7)+('Demand Forecast'!M24*Assumptions!E8)+('Demand Forecast'!M25*Assumptions!E8)+('Demand Forecast'!M26*Assumptions!E9)+('Demand Forecast'!M27*Assumptions!E9)+('Demand Forecast'!M28*Assumptions!E10)+('Demand Forecast'!M29*Assumptions!E10)+('Demand Forecast'!M30*Assumptions!E11)+('Demand Forecast'!M31*Assumptions!E11)+('Demand Forecast'!M32*Assumptions!E12)+('Demand Forecast'!M33*Assumptions!E12)+('Demand Forecast'!M34*Assumptions!E13)+('Demand Forecast'!M35*Assumptions!E13)+('Demand Forecast'!M36*Assumptions!E14)+('Demand Forecast'!M37*Assumptions!E14) -> 217700 | N7: =('Demand Forecast'!N18*Assumptions!E5)+('Demand Forecast'!N19*Assumptions!E5)+('Demand Forecast'!N20*Assumptions!E6)+('Demand Forecast'!N21*Assumptions!E6)+('Demand Forecast'!N22*Assumptions!E7)+('Demand Forecast'!N23*Assumptions!E7)+('Demand Forecast'!N24*Assumptions!E8)+('Demand Forecast'!N25*Assumptions!E8)+('Demand Forecast'!N26*Assumptions!E9)+('Demand Forecast'!N27*Assumptions!E9)+('Demand Forecast'!N28*Assumptions!E10)+('Demand Forecast'!N29*Assumptions!E10)+('Demand Forecast'!N30*Assumptions!E11)+('Demand Forecast'!N31*Assumptions!E11)+('Demand Forecast'!N32*Assumptions!E12)+('Demand Forecast'!N33*Assumptions!E12)+('Demand Forecast'!N34*Assumptions!E13)+('Demand Forecast'!N35*Assumptions!E13)+('Demand Forecast'!N36*Assumptions!E14)+('Demand Forecast'!N37*Assumptions!E14) -> 0
A8: Total Revenue | C8: =C6+C7 -> 22609.97 | D8: =D6+D7 -> 112846.66 | E8: =E6+E7 -> 146507.4 | F8: =F6+F7 -> 34931.11 | G8: =G6+G7 -> 39742.8 | H8: =H6+H7 -> 167254.48 | I8: =I6+I7 -> 219972.17 | J8: =J6+J7 -> 53639.86 | ... N8: =N6+N7 -> 74557.48
A10: COST OF GOODS SOLD
A11: Line Item | B11: Description | C11: January | D11: February | E11: March | F11: April | G11: May | H11: June | I11: July | J11: August | K11: September | L11: October | M11: November | N11: December
A12: Total Units Sold | B12: (all channels) | C12: ='Demand Forecast'!C40+'Demand Forecast'!C41+'Demand Forecast'!C42+'Demand Forecast'!C43+'Demand Forecast'!C44+'Demand Forecast'!C45+'Demand Forecast'!C46+'Demand Forecast'!C47+'Demand Forecast'!C48+'Demand Forecast'!C49 -> 203 | D12: ='Demand Forecast'!D40+'Demand Forecast'!D41+'Demand Forecast'!D42+'Demand Forecast'!D43+'Demand Forecast'!D44+'Demand Forecast'!D45+'Demand Forecast'!D46+'Demand Forecast'!D47+'Demand Forecast'!D48+'Demand Forecast'!D49 -> 544 | E12: ='Demand Forecast'!E40+'Demand Forecast'!E41+'Demand Forecast'!E42+'Demand Forecast'!E43+'Demand Forecast'!E44+'Demand Forecast'!E45+'Demand Forecast'!E46+'Demand Forecast'!E47+'Demand Forecast'!E48+'Demand Forecast'!E49 -> 680 | F12: ='Demand Forecast'!F40+'Demand Forecast'!F41+'Demand Forecast'!F42+'Demand Forecast'!F43+'Demand Forecast'!F44+'Demand Forecast'!F45+'Demand Forecast'!F46+'Demand Forecast'!F47+'Demand Forecast'!F48+'Demand Forecast'!F49 -> 289 | G12: ='Demand Forecast'!G40+'Demand Forecast'!G41+'Demand Forecast'!G42+'Demand Forecast'!G43+'Demand Forecast'!G44+'Demand Forecast'!G45+'Demand Forecast'!G46+'Demand Forecast'!G47+'Demand Forecast'!G48+'Demand Forecast'!G49 -> 320 | H12: ='Demand Forecast'!H40+'Demand Forecast'!H41+'Demand Forecast'!H42+'Demand Forecast'!H43+'Demand Forecast'!H44+'Demand Forecast'!H45+'Demand Forecast'!H46+'Demand Forecast'!H47+'Demand Forecast'!H48+'Demand Forecast'!H49 -> 797 | I12: ='Demand Forecast'!I40+'Demand Forecast'!I41+'Demand Forecast'!I42+'Demand Forecast'!I43+'Demand Forecast'!I44+'Demand Forecast'!I45+'Demand Forecast'!I46+'Demand Forecast'!I47+'Demand Forecast'!I48+'Demand Forecast'!I49 -> 1003 | J12: ='Demand Forecast'!J40+'Demand Forecast'!J41+'Demand Forecast'!J42+'Demand Forecast'!J43+'Demand Forecast'!J44+'Demand Forecast'!J45+'Demand Forecast'!J46+'Demand Forecast'!J47+'Demand Forecast'!J48+'Demand Forecast'!J49 -> 414 | ... N12: ='Demand Forecast'!N40+'Demand Forecast'!N41+'Demand Forecast'!N42+'Demand Forecast'!N43+'Demand Forecast'!N44+'Demand Forecast'!N45+'Demand Forecast'!N46+'Demand Forecast'!N47+'Demand Forecast'!N48+'Demand Forecast'!N49 -> 552
A13: COGS | B13: (units × unit cost) | C13: =('Demand Forecast'!C40*Assumptions!C5)+('Demand Forecast'!C41*Assumptions!C6)+('Demand Forecast'!C42*Assumptions!C7)+('Demand Forecast'!C43*Assumptions!C8)+('Demand Forecast'!C44*Assumptions!C9)+('Demand Forecast'!C45*Assumptions!C10)+('Demand Forecast'!C46*Assumptions!C11)+('Demand Forecast'!C47*Assumptions!C12)+('Demand Forecast'!C48*Assumptions!C13)+('Demand Forecast'!C49*Assumptions!C14) -> 8225 | D13: =('Demand Forecast'!D40*Assumptions!C5)+('Demand Forecast'!D41*Assumptions!C6)+('Demand Forecast'!D42*Assumptions!C7)+('Demand Forecast'!D43*Assumptions!C8)+('Demand Forecast'!D44*Assumptions!C9)+('Demand Forecast'!D45*Assumptions!C10)+('Demand Forecast'!D46*Assumptions!C11)+('Demand Forecast'!D47*Assumptions!C12)+('Demand Forecast'!D48*Assumptions!C13)+('Demand Forecast'!D49*Assumptions!C14) -> 47332.5 | E13: =('Demand Forecast'!E40*Assumptions!C5)+('Demand Forecast'!E41*Assumptions!C6)+('Demand Forecast'!E42*Assumptions!C7)+('Demand Forecast'!E43*Assumptions!C8)+('Demand Forecast'!E44*Assumptions!C9)+('Demand Forecast'!E45*Assumptions!C10)+('Demand Forecast'!E46*Assumptions!C11)+('Demand Forecast'!E47*Assumptions!C12)+('Demand Forecast'!E48*Assumptions!C13)+('Demand Forecast'!E49*Assumptions!C14) -> 61775 | F13: =('Demand Forecast'!F40*Assumptions!C5)+('Demand Forecast'!F41*Assumptions!C6)+('Demand Forecast'!F42*Assumptions!C7)+('Demand Forecast'!F43*Assumptions!C8)+('Demand Forecast'!F44*Assumptions!C9)+('Demand Forecast'!F45*Assumptions!C10)+('Demand Forecast'!F46*Assumptions!C11)+('Demand Forecast'!F47*Assumptions!C12)+('Demand Forecast'!F48*Assumptions!C13)+('Demand Forecast'!F49*Assumptions!C14) -> 12667.5 | G13: =('Demand Forecast'!G40*Assumptions!C5)+('Demand Forecast'!G41*Assumptions!C6)+('Demand Forecast'!G42*Assumptions!C7)+('Demand Forecast'!G43*Assumptions!C8)+('Demand Forecast'!G44*Assumptions!C9)+('Demand Forecast'!G45*Assumptions!C10)+('Demand Forecast'!G46*Assumptions!C11)+('Demand Forecast'!G47*Assumptions!C12)+('Demand Forecast'!G48*Assumptions!C13)+('Demand Forecast'!G49*Assumptions!C14) -> 14400 | H13: =('Demand Forecast'!H40*Assumptions!C5)+('Demand Forecast'!H41*Assumptions!C6)+('Demand Forecast'!H42*Assumptions!C7)+('Demand Forecast'!H43*Assumptions!C8)+('Demand Forecast'!H44*Assumptions!C9)+('Demand Forecast'!H45*Assumptions!C10)+('Demand Forecast'!H46*Assumptions!C11)+('Demand Forecast'!H47*Assumptions!C12)+('Demand Forecast'!H48*Assumptions!C13)+('Demand Forecast'!H49*Assumptions!C14) -> 69832.5 | I13: =('Demand Forecast'!I40*Assumptions!C5)+('Demand Forecast'!I41*Assumptions!C6)+('Demand Forecast'!I42*Assumptions!C7)+('Demand Forecast'!I43*Assumptions!C8)+('Demand Forecast'!I44*Assumptions!C9)+('Demand Forecast'!I45*Assumptions!C10)+('Demand Forecast'!I46*Assumptions!C11)+('Demand Forecast'!I47*Assumptions!C12)+('Demand Forecast'!I48*Assumptions!C13)+('Demand Forecast'!I49*Assumptions!C14) -> 92545 | J13: =('Demand Forecast'!J40*Assumptions!C5)+('Demand Forecast'!J41*Assumptions!C6)+('Demand Forecast'!J42*Assumptions!C7)+('Demand Forecast'!J43*Assumptions!C8)+('Demand Forecast'!J44*Assumptions!C9)+('Demand Forecast'!J45*Assumptions!C10)+('Demand Forecast'!J46*Assumptions!C11)+('Demand Forecast'!J47*Assumptions!C12)+('Demand Forecast'!J48*Assumptions!C13)+('Demand Forecast'!J49*Assumptions!C14) -> 19432.5 | K13: =('Demand Forecast'!K40*Assumptions!C5)+('Demand Forecast'!K41*Assumptions!C6)+('Demand Forecast'!K42*Assumptions!C7)+('Demand Forecast'!K43*Assumptions!C8)+('Demand Forecast'!K44*Assumptions!C9)+('Demand Forecast'!K45*Assumptions!C10)+('Demand Forecast'!K46*Assumptions!C11)+('Demand Forecast'!K47*Assumptions!C12)+('Demand Forecast'!K48*Assumptions!C13)+('Demand Forecast'!K49*Assumptions!C14) -> 21190 | L13: =('Demand Forecast'!L40*Assumptions!C5)+('Demand Forecast'!L41*Assumptions!C6)+('Demand Forecast'!L42*Assumptions!C7)+('Demand Forecast'!L43*Assumptions!C8)+('Demand Forecast'!L44*Assumptions!C9)+('Demand Forecast'!L45*Assumptions!C10)+('Demand Forecast'!L46*Assumptions!C11)+('Demand Forecast'!L47*Assumptions!C12)+('Demand Forecast'!L48*Assumptions!C13)+('Demand Forecast'!L49*Assumptions!C14) -> 91697.5 | M13: =('Demand Forecast'!M40*Assumptions!C5)+('Demand Forecast'!M41*Assumptions!C6)+('Demand Forecast'!M42*Assumptions!C7)+('Demand Forecast'!M43*Assumptions!C8)+('Demand Forecast'!M44*Assumptions!C9)+('Demand Forecast'!M45*Assumptions!C10)+('Demand Forecast'!M46*Assumptions!C11)+('Demand Forecast'!M47*Assumptions!C12)+('Demand Forecast'!M48*Assumptions!C13)+('Demand Forecast'!M49*Assumptions!C14) -> 119835 | N13: =('Demand Forecast'!N40*Assumptions!C5)+('Demand Forecast'!N41*Assumptions!C6)+('Demand Forecast'!N42*Assumptions!C7)+('Demand Forecast'!N43*Assumptions!C8)+('Demand Forecast'!N44*Assumptions!C9)+('Demand Forecast'!N45*Assumptions!C10)+('Demand Forecast'!N46*Assumptions!C11)+('Demand Forecast'!N47*Assumptions!C12)+('Demand Forecast'!N48*Assumptions!C13)+('Demand Forecast'!N49*Assumptions!C14) -> 26985
A14: Gross Profit | C14: =C8-C13 -> 14384.97 | D14: =D8-D13 -> 65514.16 | E14: =E8-E13 -> 84732.4 | F14: =F8-F13 -> 22263.61 | G14: =G8-G13 -> 25342.8 | H14: =H8-H13 -> 97421.98 | I14: =I8-I13 -> 127427.17 | J14: =J8-J13 -> 34207.36 | ... N14: =N8-N13 -> 47572.48
A15: Gross Margin % | C15: =IFERROR(C14/C8,0) -> 0.63622243 | D15: =IFERROR(D14/D8,0) -> 0.58055914 | E15: =IFERROR(E14/E8,0) -> 0.57834894 | F15: =IFERROR(F14/F8,0) -> 0.63735764 | G15: =IFERROR(G14/G8,0) -> 0.63767022 | H15: =IFERROR(H14/H8,0) -> 0.58247755 | I15: =IFERROR(I14/I8,0) -> 0.57928769 | J15: =IFERROR(J14/J8,0) -> 0.63772277 | ... N15: =IFERROR(N14/N8,0) -> 0.63806448
A17: CASH FLOW
A18: Line Item | B18: Description | C18: January | D18: February | E18: March | F18: April | G18: May | H18: June | I18: July | J18: August | K18: September | L18: October | M18: November | N18: December
A19: Cash Inflow | B19: (from sales) | C19: =C8 -> 22609.97 | D19: =D8 -> 112846.66 | E19: =E8 -> 146507.4 | F19: =F8 -> 34931.11 | G19: =G8 -> 39742.8 | H19: =H8 -> 167254.48 | I19: =I8 -> 219972.17 | J19: =J8 -> 53639.86 | ... N19: =N8 -> 74557.48
A20: Cash Outflow | B20: (inventory purchases) | C20: =-(('Inventory Model'!C8*Assumptions!C5)+('Inventory Model'!C17*Assumptions!C6)+('Inventory Model'!C26*Assumptions!C7)+('Inventory Model'!C35*Assumptions!C8)+('Inventory Model'!C44*Assumptions!C9)+('Inventory Model'!C53*Assumptions!C10)+('Inventory Model'!C62*Assumptions!C11)+('Inventory Model'!C71*Assumptions!C12)+('Inventory Model'!C80*Assumptions!C13)+('Inventory Model'!C89*Assumptions!C14)) -> 0 | D20: =-(('Inventory Model'!D8*Assumptions!C5)+('Inventory Model'!D17*Assumptions!C6)+('Inventory Model'!D26*Assumptions!C7)+('Inventory Model'!D35*Assumptions!C8)+('Inventory Model'!D44*Assumptions!C9)+('Inventory Model'!D53*Assumptions!C10)+('Inventory Model'!D62*Assumptions!C11)+('Inventory Model'!D71*Assumptions!C12)+('Inventory Model'!D80*Assumptions!C13)+('Inventory Model'!D89*Assumptions!C14)) -> 0 | E20: =-(('Inventory Model'!E8*Assumptions!C5)+('Inventory Model'!E17*Assumptions!C6)+('Inventory Model'!E26*Assumptions!C7)+('Inventory Model'!E35*Assumptions!C8)+('Inventory Model'!E44*Assumptions!C9)+('Inventory Model'!E53*Assumptions!C10)+('Inventory Model'!E62*Assumptions!C11)+('Inventory Model'!E71*Assumptions!C12)+('Inventory Model'!E80*Assumptions!C13)+('Inventory Model'!E89*Assumptions!C14)) -> 0 | F20: =-(('Inventory Model'!F8*Assumptions!C5)+('Inventory Model'!F17*Assumptions!C6)+('Inventory Model'!F26*Assumptions!C7)+('Inventory Model'!F35*Assumptions!C8)+('Inventory Model'!F44*Assumptions!C9)+('Inventory Model'!F53*Assumptions!C10)+('Inventory Model'!F62*Assumptions!C11)+('Inventory Model'!F71*Assumptions!C12)+('Inventory Model'!F80*Assumptions!C13)+('Inventory Model'!F89*Assumptions!C14)) -> 0 | G20: =-(('Inventory Model'!G8*Assumptions!C5)+('Inventory Model'!G17*Assumptions!C6)+('Inventory Model'!G26*Assumptions!C7)+('Inventory Model'!G35*Assumptions!C8)+('Inventory Model'!G44*Assumptions!C9)+('Inventory Model'!G53*Assumptions!C10)+('Inventory Model'!G62*Assumptions!C11)+('Inventory Model'!G71*Assumptions!C12)+('Inventory Model'!G80*Assumptions!C13)+('Inventory Model'!G89*Assumptions!C14)) -> 0 | H20: =-(('Inventory Model'!H8*Assumptions!C5)+('Inventory Model'!H17*Assumptions!C6)+('Inventory Model'!H26*Assumptions!C7)+('Inventory Model'!H35*Assumptions!C8)+('Inventory Model'!H44*Assumptions!C9)+('Inventory Model'!H53*Assumptions!C10)+('Inventory Model'!H62*Assumptions!C11)+('Inventory Model'!H71*Assumptions!C12)+('Inventory Model'!H80*Assumptions!C13)+('Inventory Model'!H89*Assumptions!C14)) -> 0 | I20: =-(('Inventory Model'!I8*Assumptions!C5)+('Inventory Model'!I17*Assumptions!C6)+('Inventory Model'!I26*Assumptions!C7)+('Inventory Model'!I35*Assumptions!C8)+('Inventory Model'!I44*Assumptions!C9)+('Inventory Model'!I53*Assumptions!C10)+('Inventory Model'!I62*Assumptions!C11)+('Inventory Model'!I71*Assumptions!C12)+('Inventory Model'!I80*Assumptions!C13)+('Inventory Model'!I89*Assumptions!C14)) -> 0 | J20: =-(('Inventory Model'!J8*Assumptions!C5)+('Inventory Model'!J17*Assumptions!C6)+('Inventory Model'!J26*Assumptions!C7)+('Inventory Model'!J35*Assumptions!C8)+('Inventory Model'!J44*Assumptions!C9)+('Inventory Model'!J53*Assumptions!C10)+('Inventory Model'!J62*Assumptions!C11)+('Inventory Model'!J71*Assumptions!C12)+('Inventory Model'!J80*Assumptions!C13)+('Inventory Model'!J89*Assumptions!C14)) -> 0 | K20: =-(('Inventory Model'!K8*Assumptions!C5)+('Inventory Model'!K17*Assumptions!C6)+('Inventory Model'!K26*Assumptions!C7)+('Inventory Model'!K35*Assumptions!C8)+('Inventory Model'!K44*Assumptions!C9)+('Inventory Model'!K53*Assumptions!C10)+('Inventory Model'!K62*Assumptions!C11)+('Inventory Model'!K71*Assumptions!C12)+('Inventory Model'!K80*Assumptions!C13)+('Inventory Model'!K89*Assumptions!C14)) -> 0 | L20: =-(('Inventory Model'!L8*Assumptions!C5)+('Inventory Model'!L17*Assumptions!C6)+('Inventory Model'!L26*Assumptions!C7)+('Inventory Model'!L35*Assumptions!C8)+('Inventory Model'!L44*Assumptions!C9)+('Inventory Model'!L53*Assumptions!C10)+('Inventory Model'!L62*Assumptions!C11)+('Inventory Model'!L71*Assumptions!C12)+('Inventory Model'!L80*Assumptions!C13)+('Inventory Model'!L89*Assumptions!C14)) -> 0 | M20: =-(('Inventory Model'!M8*Assumptions!C5)+('Inventory Model'!M17*Assumptions!C6)+('Inventory Model'!M26*Assumptions!C7)+('Inventory Model'!M35*Assumptions!C8)+('Inventory Model'!M44*Assumptions!C9)+('Inventory Model'!M53*Assumptions!C10)+('Inventory Model'!M62*Assumptions!C11)+('Inventory Model'!M71*Assumptions!C12)+('Inventory Model'!M80*Assumptions!C13)+('Inventory Model'!M89*Assumptions!C14)) -> 0 | N20: =-(('Inventory Model'!N8*Assumptions!C5)+('Inventory Model'!N17*Assumptions!C6)+('Inventory Model'!N26*Assumptions!C7)+('Inventory Model'!N35*Assumptions!C8)+('Inventory Model'!N44*Assumptions!C9)+('Inventory Model'!N53*Assumptions!C10)+('Inventory Model'!N62*Assumptions!C11)+('Inventory Model'!N71*Assumptions!C12)+('Inventory Model'!N80*Assumptions!C13)+('Inventory Model'!N89*Assumptions!C14)) -> 0
A21: Net Cash Flow | C21: =C19+C20 -> 22609.97 | D21: =D19+D20 -> 112846.66 | E21: =E19+E20 -> 146507.4 | F21: =F19+F20 -> 34931.11 | G21: =G19+G20 -> 39742.8 | H21: =H19+H20 -> 167254.48 | I21: =I19+I20 -> 219972.17 | J21: =J19+J20 -> 53639.86 | ... N21: =N19+N20 -> 74557.48

Sheet Executive Dashboard
B2: CLUB GIRL GOLF
B3: Inventory & Financial Dashboard
B5: 📊 KEY METRICS
B7: =SUM('Financial Summary'!C8:N8) -> 1436607.6 | D7: =AVERAGE('Financial Summary'!C15:N15) -> 0.6091624 | F7: =SUM('Financial Summary'!C12:N12) -> 7595 | H7: =SUM(Assumptions!H5:H14) -> 2950 | J7: =SUMPRODUCT((Assumptions!H5:H14<Assumptions!G5:G14)*1) -> 0 | L7: =SUMPRODUCT(Assumptions!C5:C14,Assumptions!H5:H14) -> 124500
B9: Total Revenue (YTD) | D9: Gross Margin % | F9: Total Units Sold | H9: Inventory On Hand | J9: SKUs Below Safety | L9: Cash in Inventory
B11: 📦 INVENTORY RUNWAY | H11: 💰 REVENUE BREAKDOWN
B12: SKU | C12: Stock | D12: Daily Sales | E12: Days Left | F12: Stockout Date | G12: Status | H12: Month | I12: DTC | J12: Wholesale | K12: Total | L12: Margin %
B13: =Assumptions!A5 -> SKU001 | C13: =Assumptions!H5 -> 250 | D13: =SUM('Demand Forecast'!C40:N40)/365 -> 3.830137 | E13: =IF(D13=0,"∞",C13/D13) -> 65.271817 | F13: =IF(E13="∞","Never",TEXT(TODAY()+E13,"mmm dd")) -> Apr 18 | G13: =IF(E13="∞","✅ OK",IF(E13<30,"🚨 URGENT",IF(E13<60,"⚠️ SOON","✅ OK"))) -> ✅ OK | H13: Jan | I13: ='Financial Summary'!C6 -> 22609.97 | J13: ='Financial Summary'!C7 -> 0 | K13: ='Financial Summary'!C8 -> 22609.97 | L13: ='Financial Summary'!C15 -> 0.63622243
B14: =Assumptions!A6 -> SKU002 | C14: =Assumptions!H6 -> 180 | D14: =SUM('Demand Forecast'!C41:N41)/365 -> 2.8136986 | E14: =IF(D14=0,"∞",C14/D14) -> 63.972736 | F14: =IF(E14="∞","Never",TEXT(TODAY()+E14,"mmm dd")) -> Apr 16 | G14: =IF(E14="∞","✅ OK",IF(E14<30,"🚨 URGENT",IF(E14<60,"⚠️ SOON","✅ OK"))) -> ✅ OK | H14: Feb | I14: ='Financial Summary'!D6 -> 27421.66 | J14: ='Financial Summary'!D7 -> 85425 | K14: ='Financial Summary'!D8 -> 112846.66 | L14: ='Financial Summary'!D15 -> 0.58055914
B15: =Assumptions!A7 -> SKU003 | C15: =Assumptions!H7 -> 150 | D15: =SUM('Demand Forecast'!C42:N42)/365 -> 2.2849315 | E15: =IF(D15=0,"∞",C15/D15) -> 65.647482 | F15: =IF(E15="∞","Never",TEXT(TODAY()+E15,"mmm dd")) -> Apr 18 | G15: =IF(E15="∞","✅ OK",IF(E15<30,"🚨 URGENT",IF(E15<60,"⚠️ SOON","✅ OK"))) -> ✅ OK | H15: Mar | I15: ='Financial Summary'!E6 -> 30807.4 | J15: ='Financial Summary'!E7 -> 115700 | K15: ='Financial Summary'!E8 -> 146507.4 | L15: ='Financial Summary'!E15 -> 0.57834894
B16: =Assumptions!A8 -> SKU004 | C16: =Assumptions!H8 -> 120 | D16: =SUM('Demand Forecast'!C43:N43)/365 -> 1.709589 | E16: =IF(D16=0,"∞",C16/D16) -> 70.192308 | F16: =IF(E16="∞","Never",TEXT(TODAY()+E16,"mmm dd")) -> Apr 23 | G16: =IF(E16="∞","✅ OK",IF(E16<30,"🚨 URGENT",IF(E16<60,"⚠️ SOON","✅ OK"))) -> ✅ OK | H16: Apr | I16: ='Financial Summary'!F6 -> 34931.11 | J16: ='Financial Summary'!F7 -> 0 | K16: ='Financial Summary'!F8 -> 34931.11 | L16: ='Financial Summary'!F15 -> 0.63735764
B17: =Assumptions!A9 -> SKU005 | C17: =Assumptions!H9 -> 110 | D17: =SUM('Demand Forecast'!C44:N44)/365 -> 1.5506849 | E17: =IF(D17=0,"∞",C17/D17) -> 70.936396 | F17: =IF(E17="∞","Never",TEXT(TODAY()+E17,"mmm dd")) -> Apr 23 | G17: =IF(E17="∞","✅ OK",IF(E17<30,"🚨 URGENT",IF(E17<60,"⚠️ SOON","✅ OK"))) -> ✅ OK | H17: May | I17: ='Financial Summary'!G6 -> 39742.8 | J17: ='Financial Summary'!G7 -> 0 | K17: ='Financial Summary'!G8 -> 39742.8 | L17: ='Financial Summary'!G15 -> 0.63767022
B18: =Assumptions!A10 -> SKU006 | C18: =Assumptions!H10 -> 90 | D18: =SUM('Demand Forecast'!C45:N45)/365 -> 0.53150685 | E18: =IF(D18=0,"∞",C18/D18) -> 169.3299 | F18: =IF(E18="∞","Never",TEXT(TODAY()+E18,"mmm dd")) -> Jul 31 | G18: =IF(E18="∞","✅ OK",IF(E18<30,"🚨 URGENT",IF(E18<60,"⚠️ SOON","✅ OK"))) -> ✅ OK | H18: Jun | I18: ='Financial Summary'!H6 -> 44604.48 | J18: ='Financial Summary'!H7 -> 122650 | K18: ='Financial Summary'!H8 -> 167254.48 | L18: ='Financial Summary'!H15 -> 0.58247755
B19: =Assumptions!A11 -> SKU007 | C19: =Assumptions!H11 -> 800 | D19: =SUM('Demand Forecast'!C46:N46)/365 -> 2.5616438 | E19: =IF(D19=0,"∞",C19/D19) -> 312.29947 | F19: =IF(E19="∞","Never",TEXT(TODAY()+E19,"mmm dd")) -> Dec 21 | G19: =IF(E19="∞","✅ OK",IF(E19<30,"🚨 URGENT",IF(E19<60,"⚠️ SOON","✅ OK"))) -> ✅ OK | H19: Jul | I19: ='Financial Summary'!I6 -> 49122.17 | J19: ='Financial Summary'!I7 -> 170850 | K19: ='Financial Summary'!I8 -> 219972.17 | L19: ='Financial Summary'!I15 -> 0.57928769
B20: =Assumptions!A12 -> SKU008 | C20: =Assumptions!H12 -> 600 | D20: =SUM('Demand Forecast'!C47:N47)/365 -> 2.2191781 | E20: =IF(D20=0,"∞",C20/D20) -> 270.37037 | F20: =IF(E20="∞","Never",TEXT(TODAY()+E20,"mmm dd")) -> Nov 09 | G20: =IF(E20="∞","✅ OK",IF(E20<30,"🚨 URGENT",IF(E20<60,"⚠️ SOON","✅ OK"))) -> ✅ OK | H20: Aug | I20: ='Financial Summary'!J6 -> 53639.86 | J20: ='Financial Summary'!J7 -> 0 | K20: ='Financial Summary'!J8 -> 53639.86 | L20: ='Financial Summary'!J15 -> 0.63772277
B21: =Assumptions!A13 -> SKU009 | C21: =Assumptions!H13 -> 350 | D21: =SUM('Demand Forecast'!C48:N48)/365 -> 1.890411 | E21: =IF(D21=0,"∞",C21/D21) -> 185.14493 | F21: =IF(E21="∞","Never",TEXT(TODAY()+E21,"mmm dd")) -> Aug 16 | G21: =IF(E21="∞","✅ OK",IF(E21<30,"🚨 URGENT",IF(E21<60,"⚠️ SOON","✅ OK"))) -> ✅ OK | H21: Sep | I21: ='Financial Summary'!K6 -> 58501.54 | J21: ='Financial Summary'!K7 -> 0 | K21: ='Financial Summary'!K8 -> 58501.54 | L21: ='Financial Summary'!K15 -> 0.63778731
B22: =Assumptions!A14 -> SKU010 | C22: =Assumptions!H14 -> 300 | D22: =SUM('Demand Forecast'!C49:N49)/365 -> 1.4164384 | E22: =IF(D22=0,"∞",C22/D22) -> 211.79884 | F22: =IF(E22="∞","Never",TEXT(TODAY()+E22,"mmm dd")) -> Sep 11 | G22: =IF(E22="∞","✅ OK",IF(E22<30,"🚨 URGENT",IF(E22<60,"⚠️ SOON","✅ OK"))) -> ✅ OK | H22: Oct | I22: ='Financial Summary'!L6 -> 63363.22 | J22: ='Financial Summary'!L7 -> 157100 | K22: ='Financial Summary'!L8 -> 220463.22 | L22: ='Financial Summary'!L15 -> 0.58406894
H23: Nov | I23: ='Financial Summary'!M6 -> 67880.91 | J23: ='Financial Summary'!M7 -> 217700 | K23: ='Financial Summary'!M8 -> 285580.91 | L23: ='Financial Summary'!M15 -> 0.58038162
H24: Dec | I24: ='Financial Summary'!N6 -> 74557.48 | J24: ='Financial Summary'!N7 -> 0 | K24: ='Financial Summary'!N8 -> 74557.48 | L24: ='Financial Summary'!N15 -> 0.63806448
B25: 📈 INVENTORY SAWTOOTH - SKU001
B26: Month | C26: Jan | D26: Feb | E26: Mar | F26: Apr | G26: May | H26: Jun | I26: Jul | J26: Aug | K26: Sep | L26: Oct | M26: Nov | N26: Dec
B27: Ending Inv | C27: ='Inventory Model'!C9 -> 235 | D27: ='Inventory Model'!D9 -> 117 | E27: ='Inventory Model'!E9 -> 0 | F27: ='Inventory Model'!F9 -> 0 | G27: ='Inventory Model'!G9 -> 0 | H27: ='Inventory Model'!H9 -> 0 | I27: ='Inventory Model'!I9 -> 0 | J27: ='Inventory Model'!J9 -> 0 | ... N27: ='Inventory Model'!N9 -> 0
